Workbook
Name IQ_CH: 110000
Name IQ_CQ: 5000
Name IQ_CY: 10000
Name IQ_DAILY: 500000
Name IQ_FH: 100000
Name IQ_FQ: 500
Name IQ_FY: 1000
Name IQ_LTM: 2000
Name IQ_MONTH: 15000
Name IQ_NTM: 6000
Name IQ_WEEK: 50000
Name IQ_YTD: 3000
Name UPDATE: 'Data Sheet'!$E$1

Sheet One page Profile
B2: INFOSYS LTD - ONE PAGE PROFILE
B15: Competitive Strengths | D15: Key Risks | G15: Key Business Areas
B17: Strong global brand | D17: Global IT spending slowdown | G17: 1) Digital Transformation | J17: 4) Application Services
B18: Large skilled workforce | D18: Intense industry competition | G18: Cloud • AI • Automation | J18: Development • Maintenance
B19: Long-term enterprise clients | D19: Employee attrition and wage inflation | G19: 2) Consulting | J19: 5) Cybersecurity
B20: Strong balance sheet | D20: Currency fluctuations | G20: Strategy • Technology Consulting | J20: Security • Risk Management
B21: Global delivery model | D21: Rapid technological changes | G21: 3) Data & Analytics | J21: 6) Engineering Services
B22: Broad digital capabilities | D22: AI disruption | G22: Data Analytics • AI Solutions | J22: Product Engineering • R&D
B23: Strong cash generation | D23: Dependence on international markets
B27: Key Financial Metrics | H27: ='Ratio Analysis'!J3 -> 45007 | I27: ='Ratio Analysis'!K3 -> 45373 | J27: ='Ratio Analysis'!L3 -> 45739 | K27: ='Ratio Analysis'!M3 -> 46105
B29: Total sales | H29: ='Data Sheet'!H17 -> 146767 | I29: ='Data Sheet'!I17 -> 153670 | J29: ='Data Sheet'!J17 -> 162990 | K29: ='Data Sheet'!K17 -> 178650
B30: Sales growth | H30: ='Ratio Analysis'!J5 -> 0.20655864 | I30: ='Ratio Analysis'!K5 -> 0.047033734 | J30: ='Ratio Analysis'!L5 -> 0.060649444 | K30: ='Ratio Analysis'!M5 -> 0.096079514
B31: Gross Profit Margins (%) | H31: ='Ratio Analysis'!J11 -> 0.28539794 | I31: ='Ratio Analysis'!K11 -> 0.28398516 | J31: ='Ratio Analysis'!L11 -> 0.28471072 | K31: ='Ratio Analysis'!M11 -> 0.28207669
B32: EBITDA Margins (%) | H32: ='Ratio Analysis'!J12 -> 0.23935898 | I32: ='Ratio Analysis'!K12 -> 0.2370339 | J32: ='Ratio Analysis'!L12 -> 0.24072642 | K32: ='Ratio Analysis'!M12 -> 0.23666387
B33: EBIT Margins (%) | H33: ='Ratio Analysis'!I13 -> 0.23030886 | I33: ='Ratio Analysis'!J13 -> 0.21057186 | J33: ='Ratio Analysis'!K13 -> 0.20659205 | K33: ='Ratio Analysis'!L13 -> 0.21120314
B34: Net Profit Margins (%) | H34: ='Ratio Analysis'!J15 -> 0.14585704 | I34: ='Ratio Analysis'!K15 -> 0.14015097 | J34: ='Ratio Analysis'!L15 -> 0.14203325 | K34: ='Ratio Analysis'!M15 -> 0.14800448
B35: Earnings Per Share | H35: =HistoricalFS!I38 -> 51.60054 | I35: =HistoricalFS!J38 -> 51.885133 | J35: =HistoricalFS!K38 -> 55.73881 | K35: =HistoricalFS!L38 -> 65.196272
B36: EPS Growth (%) | H36: =HistoricalFS!I39 -> 0.093486431 | I36: =HistoricalFS!J39 -> 0.0055153183 | J36: =HistoricalFS!K39 -> 0.074273236 | K36: =HistoricalFS!L39 -> 0.16967463
B37: Dividend Per Share (%) | H37: =HistoricalFS!I41 -> 33.913127 | I37: =HistoricalFS!J41 -> 45.901371 | J37: =HistoricalFS!K41 -> 42.924422 | K37: =HistoricalFS!L41 -> 47.91005
B38: DPS Growth (%) | H38: =(HistoricalFS!I41-HistoricalFS!H41)/HistoricalFS!H41 -> 0.096761529 | I38: =(HistoricalFS!J41-HistoricalFS!I41)/HistoricalFS!I41 -> 0.35349861 | J38: =(HistoricalFS!K41-HistoricalFS!J41)/HistoricalFS!J41 -> -0.064855345 | K38: =(HistoricalFS!L41-HistoricalFS!K41)/HistoricalFS!K41 -> 0.116149
B40: Key Financial Ratios | H40: =H27 -> 45007 | I40: =I27 -> 45373 | J40: =J27 -> 45739 | K40: =K27 -> 46105
B42: Return On Equity (%) | H42: ='Ratio Analysis'!J23 -> 0.28388611 | I42: ='Ratio Analysis'!K23 -> 0.24441645 | J42: ='Ratio Analysis'!L23 -> 0.24160387 | K42: ='Ratio Analysis'!M23 -> 0.284765
B43: Return On Capital Employed (%) | H43: ='Ratio Analysis'!J21 -> 0.3692089 | I43: ='Ratio Analysis'!K21 -> 0.32906971 | J43: ='Ratio Analysis'!L21 -> 0.33085684 | K43: ='Ratio Analysis'!M21 -> 0.36635041
B44: Retained Earnings (%) | H44: ='Ratio Analysis'!J22 -> 0.34277573 | I44: ='Ratio Analysis'!K22 -> 0.11532711 | J44: ='Ratio Analysis'!L22 -> 0.22990065 | K44: ='Ratio Analysis'!M22 -> 0.26514126
B45: Self Sustained Growth Rate | H45: ='Ratio Analysis'!J24 -> 0.097309268 | I45: ='Ratio Analysis'!K24 -> 0.028187843 | J45: ='Ratio Analysis'!L24 -> 0.055544887 | K45: ='Ratio Analysis'!M24 -> 0.075502951
B47: SHAREHOLDING PATTERN | H47: 45809 | I47: 45901 | J47: 45992 | K47: 46082
B49: Promoters | H49: 0.1461 | I49: 0.143 | J49: 0.1452 | K49: 0.1438
B50: FIIs | H50: 0.3192 | I50: 0.3008 | J50: 0.3027 | K50: 0.2845
B51: DIIs | H51: 0.3939 | I51: 0.4146 | J51: 0.4108 | K51: 0.4319
B52: Government | H52: 0.0021 | I52: 0.002 | J52: 0.002 | K52: 0.002
B53: Public | H53: 0.1362 | I53: 0.137 | J53: 0.1369 | K53: 0.1354
B54: Others | H54: 0.0025 | I54: 0.0024 | J54: 0.0024 | K54: 0.0023
B55: No. of Shareholders | H55: 25,79,164 | I55: 27,19,353 | J55: 26,31,803 | K55: 27,48,596

Sheet Data>

Sheet Data Sheet
A1: COMPANY NAME | B1: INFOSYS LTD | E1: =IF(B2<>B3, "A NEW VERSION OF THE WORKSHEET IS AVAILABLE", "")
A2: LATEST VERSION | B2: 2.1 | E2: PLEASE DO NOT MAKE ANY CHANGES TO THIS SHEET
A3: CURRENT VERSION | B3: 2.1
A5: META
A6: Number of shares | B6: =IF(B9>0, B9/B8, 0) -> 405.80564
A7: Face Value | B7: 5
A8: Current Price | B8: 1130.6
A9: Market Capitalization | B9: 458803.86
A15: PROFIT & LOSS | B15: =B26+B34 -> 23357 | K15: =K17-K18-K20-K21-K22-K23-K19 -> 43609
A16: Report Date | B16: 42825 | C16: 43190 | D16: 43555 | E16: 43921 | F16: 44286 | G16: 44651 | H16: 45016 | I16: 45382 | J16: 45747 | K16: 46112
A17: Sales | B17: 68484 | C17: 70522 | D17: 82675 | E17: 90791 | F17: 100472 | G17: 121641 | H17: 146767 | I17: 153670 | J17: 162990 | K17: 178650
A18: Raw Material Cost
A19: Change in Inventory
A20: Power and Fuel | B20: 228 | C20: 207 | D20: 221 | E20: 229 | F20: 143 | G20: 132 | H20: 176 | I20: 199 | J20: 222 | K20: 223
A21: Other Mfr. Exp | B21: 6712 | C21: 7286 | D21: 9902 | E21: 11086 | F21: 12800 | G21: 20690 | H21: 26330 | I21: 27195 | J21: 30395 | K21: 32922
A22: Employee Cost | B22: 37669 | C22: 38902 | D22: 45323 | E22: 50895 | F22: 55547 | G22: 63997 | H22: 78374 | I22: 82636 | J22: 85968 | K22: 95112
A23: Selling and admin | B23: 4584 | C23: 4585 | D23: 5553 | E23: 5375 | F23: 3194 | G23: 4305 | H23: 5300 | I23: 5705 | J23: 6039 | K23: 6784
A24: Other Expenses | B24: 687 | C24: 720 | D24: 1506 | E24: 939 | F24: 899 | G24: 1026 | H24: 1457 | I24: 1510 | J24: 1130 | K24: 1329
A25: Other Income | B25: 3050 | C25: 3311 | D25: 2882 | E25: 2803 | F25: 2201 | G25: 2295 | H25: 2701 | I25: 4711 | J25: 3600 | K25: 3033
A26: Depreciation | B26: 1703 | C26: 1863 | D26: 2011 | E26: 2893 | F26: 3267 | G26: 3476 | H26: 4225 | I26: 4678 | J26: 4812 | K26: 4902
A27: Interest | E27: 170 | F27: 195 | G27: 200 | H27: 284 | I27: 470 | J27: 416 | K27: 416
A28: Profit before tax | B28: 19951 | C28: 20270 | D28: 21041 | E28: 22007 | F28: 26628 | G28: 30110 | H28: 33322 | I28: 35988 | J28: 37608 | K28: 39995
A29: Tax | B29: 5598 | C29: 4241 | D29: 5631 | E29: 5368 | F29: 7205 | G29: 7964 | H29: 9214 | I29: 9740 | J29: 10858 | K29: 10521
A30: Net profit | B30: 14353 | C30: 16029 | D30: 15404 | E30: 16594 | F30: 19351 | G30: 22110 | H30: 24095 | I30: 26233 | J30: 26713 | K30: 29440
A31: Dividend Amount | B31: 5891.6 | C31: 9465.6 | D31: 9222.5 | E31: 7427 | F31: 11469.6 | G31: 13007.6 | H31: 14069.2 | I31: 19053.2 | J31: 17827.8 | K31: 19430.4
A32: Effective Tax Rate | B32: =B29/B28 -> 0.28058744 | C32: =C29/C28 -> 0.20922546 | D32: =D29/D28 -> 0.26762036 | E32: =E29/E28 -> 0.24392239 | F32: =F29/F28 -> 0.27057984 | G32: =G29/G28 -> 0.26449684 | H32: =H29/H28 -> 0.27651401 | I32: =I29/I28 -> 0.27064577 | ... K32: =K29/K28 -> 0.26305788
A34: EBITDA | B34: =+B30+B29+B27+B26 -> 21654 | C34: =+C30+C29+C27+C26 -> 22133 | D34: =+D30+D29+D27+D26 -> 23046 | E34: =+E30+E29+E27+E26 -> 25025 | F34: =+F30+F29+F27+F26 -> 30018 | G34: =+G30+G29+G27+G26 -> 33750 | H34: =+H30+H29+H27+H26 -> 37818 | I34: =+I30+I29+I27+I26 -> 41121 | ... K34: =+K30+K29+K27+K26 -> 45279
A40: Quarters
A41: Report Date | B41: 45382 | C41: 45473 | D41: 45565 | E41: 45657 | F41: 45747 | G41: 45838 | H41: 45930 | I41: 46022 | J41: 46112 | K41: 46203
A42: Sales | B42: 37923 | C42: 39315 | D42: 40986 | E42: 41764 | F42: 40925 | G42: 42279 | H42: 44490 | I42: 45479 | J42: 46402 | K42: 48211
A43: Expenses | B43: 29139 | C43: 29878 | D43: 31177 | E43: 31649 | F43: 31051 | G43: 32336 | H43: 33955 | I43: 34845 | J43: 35235 | K43: 36802
A44: Other Income | B44: 2729 | C44: 838 | D44: 712 | E44: 859 | F44: 1190 | G44: 1042 | H44: 982 | I44: -150 | J44: 1159 | K44: 984
A45: Depreciation | B45: 1163 | C45: 1149 | D45: 1160 | E45: 1203 | F45: 1299 | G45: 1140 | H45: 1182 | I45: 1155 | J45: 1424 | K45: 1246
A46: Interest | B46: 110 | C46: 105 | D46: 108 | E46: 101 | F46: 102 | G46: 105 | H46: 106 | I46: 100 | J46: 105 | K46: 119
A47: Profit before tax | B47: 10240 | C47: 9021 | D47: 9253 | E47: 9670 | F47: 9663 | G47: 9740 | H47: 10229 | I47: 9229 | J47: 10797 | K47: 11028
A48: Tax | B48: 2265 | C48: 2647 | D48: 2737 | E48: 2848 | F48: 2625 | G48: 2816 | H48: 2854 | I48: 2563 | J48: 2288 | K48: 3253
A49: Net profit | B49: 7969 | C49: 6368 | D49: 6506 | E49: 6806 | F49: 7033 | G49: 6921 | H49: 7364 | I49: 6654 | J49: 8501 | K49: 7769
A50: Operating Profit | B50: 8784 | C50: 9437 | D50: 9809 | E50: 10115 | F50: 9874 | G50: 9943 | H50: 10535 | I50: 10634 | J50: 11167 | K50: 11409
A51: EBITDA | B51: =B49+B48+B46+B45 -> 11507 | C51: =C49+C48+C46+C45 -> 10269 | D51: =D49+D48+D46+D45 -> 10511 | E51: =E49+E48+E46+E45 -> 10958 | F51: =F49+F48+F46+F45 -> 11059 | G51: =G49+G48+G46+G45 -> 10982 | H51: =H49+H48+H46+H45 -> 11506 | I51: =I49+I48+I46+I45 -> 10472 | ... K51: =K49+K48+K46+K45 -> 12387
A55: BALANCE SHEET
A56: Report Date | B56: 42825 | C56: 43190 | D56: 43555 | E56: 43921 | F56: 44286 | G56: 44651 | H56: 45016 | I56: 45382 | J56: 45747 | K56: 46112
A57: Equity Share Capital | B57: 1144 | C57: 1088 | D57: 2170 | E57: 2122 | F57: 2124 | G57: 2098 | H57: 2069 | I57: 2071 | J57: 2073 | K57: 2024
A58: Reserves | B58: 67838 | C58: 63835 | D58: 62778 | E58: 63328 | F58: 74227 | G58: 73252 | H58: 73338 | I58: 86045 | J58: 93745 | K58: 90828
A59: Borrowings | E59: 4633 | F59: 5325 | G59: 5474 | H59: 8299 | I59: 8359 | J59: 8227 | K59: 9176
A60: Other Liabilities | B60: 14166 | C60: 14426 | D60: 19118 | E60: 21717 | F60: 25835 | G60: 35905 | H60: 40890 | I60: 39545 | J60: 43750 | K60: 52260
A61: Total | B61: 83148 | C61: 79349 | D61: 84066 | E61: 91800 | F61: 107511 | G61: 116729 | H61: 124596 | I61: 136020 | J61: 147795 | K61: 154288
A62: Net Block | B62: 14179 | C62: 12574 | D62: 15710 | E62: 23789 | F62: 25505 | G62: 25800 | H62: 29225 | I62: 27622 | J62: 30961 | K62: 33770
A63: Capital Work in Progress | B63: 1365 | C63: 1606 | D63: 1388 | E63: 954 | F63: 922 | G63: 416 | H63: 288 | I63: 293 | J63: 814 | K63: 526
A64: Investments | B64: 16423 | C64: 12163 | D64: 11261 | E64: 8792 | F64: 14205 | G64: 20324 | H64: 19478 | I64: 24623 | J64: 23541 | K64: 21880
A65: Other Assets | B65: 51181 | C65: 53006 | D65: 55707 | E65: 58265 | F65: 66879 | G65: 70189 | H65: 75605 | I65: 83482 | J65: 92479 | K65: 98112
A66: Total | B66: 83148 | C66: 79349 | D66: 84066 | E66: 91800 | F66: 107511 | G66: 116729 | H66: 124596 | I66: 136020 | J66: 147795 | K66: 154288
A67: Receivables | B67: 12322 | C67: 13142 | D67: 14827 | E67: 18487 | F67: 19294 | G67: 22698 | H67: 25424 | I67: 30193 | J67: 31158 | K67: 35234
A68: Inventory
A69: Cash & Bank | B69: 22625 | C69: 19818 | D69: 19568 | E69: 18649 | F69: 24714 | G69: 17472 | H69: 12173 | I69: 14786 | J69: 24455 | K69: 22201
A70: No. of Equity Shares | B70: 2285655150 | C70: 2173312301 | D70: 4335954462 | E70: 4240753210 | F70: 4245146114 | G70: 4193012929 | H70: 4136387925 | I70: 4139950635 | J70: 4143607528 | K70: 4046940812
A71: New Bonus Shares | D71: 2184191490
A72: Face value | B72: 5 | C72: 5 | D72: 5 | E72: 5 | F72: 5 | G72: 5 | H72: 5 | I72: 5 | J72: 5 | K72: 5
H73: =H62-G62+H45 -> 4607 | I73: =I62-H62+I45 -> -448 | J73: =J62-I62+J45 -> 4763 | K73: =K62-J62+K45 -> 4055
A80: CASH FLOW:
A81: Report Date | B81: 42825 | C81: 43190 | D81: 43555 | E81: 43921 | F81: 44286 | G81: 44651 | H81: 45016 | I81: 45382 | J81: 45747 | K81: 46112
A82: Cash from Operating Activity | B82: 11531 | C82: 13218 | D82: 14841 | E82: 17003 | F82: 23224 | G82: 23885 | H82: 22467 | I82: 25210 | J82: 35694 | K82: 33986
A83: Cash from Investing Activity | B83: -14664 | C83: 4533 | D83: -632 | E83: -331 | F83: -7373 | G83: -6485 | H83: -1071 | I83: -5093 | J83: -1864 | K83: 3546
A84: Cash from Financing Activity | B84: -6939 | C84: -20505 | D84: -14512 | E84: -17591 | F84: -9786 | G84: -24642 | H84: -26695 | I84: -17504 | J84: -24161 | K84: -39786
A85: Net Cash Flow | B85: -10072 | C85: -2754 | D85: -303 | E85: -919 | F85: 6065 | G85: -7242 | H85: -5299 | I85: 2613 | J85: 9669 | K85: -2254
A90: PRICE: | B90: 511.13 | C90: 565.9 | D90: 743.85 | E90: 641.5 | F90: 1368.05 | G90: 1906.85 | H90: 1427.95 | I90: 1498.05 | J90: 1570.65 | K90: 1250.6
A92: DERIVED:
A93: Adjusted Equity Shares in Cr | B93: 459.39 | C93: 436.82 | D93: 436.89 | E93: 425.9 | F93: 426.07 | G93: 420.67 | H93: 414.86 | I93: 415.09 | J93: 415.33 | K93: 405.56

Sheet Raw Data
C4: Mar 2015 | D4: 42430 | E4: 42795 | F4: 43160 | G4: 43525 | H4: 43891 | I4: 44256 | J4: 44621 | K4: 44986 | L4: 45352 | M4: 45717 | N4: 46082
B5: Equity Capital | C5: 572 | D5: 1144 | E5: 1144 | F5: 1088 | G5: 2170 | H5: 2122 | I5: 2124 | J5: 2098 | K5: 2069 | L5: 2071 | M5: 2073 | N5: 2024
B6: Reserves | C6: 50164 | D6: 60600 | E6: 67838 | F6: 63835 | G6: 62778 | H6: 63328 | I6: 74227 | J6: 73252 | K6: 73338 | L6: 86045 | M6: 93745 | N6: 90828
B7: Borrowings | C7: 0 | D7: 0 | E7: 0 | F7: 0 | G7: 0 | H7: 4633 | I7: 5325 | J7: 5474 | K7: 8299 | L7: 8359 | M7: 8227 | N7: 9176
B8: Lease Liabilities | C8: 0 | D8: 0 | E8: 0 | F8: 0 | G8: 0 | H8: 4633 | I8: 5325 | J8: 5474 | K8: 8299 | L8: 8359 | M8: 8227 | N8: 9176
B9: Other Liabilities | C9: 15553 | D9: 13354 | E9: 14166 | F9: 14426 | G9: 19118 | H9: 21717 | I9: 25835 | J9: 35905 | K9: 40890 | L9: 39545 | M9: 43750 | N9: 52260
B10: Non controlling int | C10: 0 | D10: 0 | E10: 0 | F10: 1 | G10: 58 | H10: 394 | I10: 431 | J10: 386 | K10: 388 | L10: 345 | M10: 385 | N10: 445
B11: Trade Payables | C11: 140 | D11: 386 | E11: 367 | F11: 694 | G11: 1655 | H11: 2852 | I11: 2645 | J11: 4134 | K11: 3865 | L11: 3956 | M11: 4164 | N11: 4744
B12: Advance from Customers | C12: 27 | D12: 28 | E12: 0 | F12: 0 | G12: 0 | H12: 0 | I12: 0 | J12: 0 | K12: 0 | L12: 0 | M12: 0 | N12: 0
B13: Other liability items | C13: 15386 | D13: 12940 | E13: 13799 | F13: 13731 | G13: 17405 | H13: 18471 | I13: 22759 | J13: 31385 | K13: 36637 | L13: 35244 | M13: 39201 | N13: 47071
B14: Total Liabilities | C14: 66289 | D14: 75098 | E14: 83148 | F14: 79349 | G14: 84066 | H14: 91800 | I14: 107511 | J14: 116729 | K14: 124596 | L14: 136020 | M14: 147795 | N14: 154288
B15: Fixed Assets | C15: 11346 | D15: 13386 | E15: 14179 | F15: 12574 | G15: 15710 | H15: 23789 | I15: 25505 | J15: 25800 | K15: 29225 | L15: 27622 | M15: 30961 | N15: 33770
B16: Land | C16: 1564 | D16: 1622 | E16: 1095 | F16: 1229 | G16: 1307 | H16: 1950 | I16: 2035 | J16: 2066 | K16: 2054 | L16: 2037 | M16: 2079 | N16: 1990
... B34: Total Assets | C34: 66289 | D34: 75098 | E34: 83148 | F34: 79349 | G34: 84066 | H34: 91800 | I34: 107511 | J34: 116729 | K34: 124596 | L34: 136020 | M34: 147795 | N34: 154288

Sheet Cash Flow Data
C2: 42795 | D2: 43160 | E2: 43525 | F2: 43891 | G2: 44256 | H2: 44621 | I2: 44986 | J2: 45352 | K2: 45717 | L2: 46082
B3: Cash from Operating Activity | C3: 11531 | D3: 13218 | E3: 14841 | F3: 17003 | G3: 23224 | H3: 23885 | I3: 22467 | J3: 25210 | K3: 35694 | L3: 33986
B4: Profit from operations | C4: 19340 | D4: 19963 | E4: 22126 | F4: 23920 | G4: 28845 | H4: 32921 | I4: 37605 | J4: 39523 | K4: 41591 | L4: 45273
B5: Receivables | C5: -1743 | D5: -1523 | E5: -2881 | F5: -3861 | G5: -1835 | H5: -7937 | I5: -7076 | J5: -2667 | K5: -1769 | L5: -5177
B6: Payables | C6: -19 | D6: 328 | E6: 916 | F6: -373 | G6: -245 | H6: 1489 | I6: -279 | J6: 91 | K6: 176 | L6: -26
B7: Loans Advances | C7: 0 | D7: 0 | E7: 0 | F7: 0 | G7: -534 | H7: -1914 | I7: -3108 | J7: -1172 | K7: -1024 | L7: -2645
B8: Other WC items | C8: -394 | D8: 1279 | E8: 1512 | F8: 1867 | G8: 3382 | H8: 6938 | I8: 4119 | J8: -1334 | K8: 2322 | L8: 5209
B9: Direct taxes | C9: -5653 | D9: -6829 | E9: -6832 | F9: -4550 | G9: -6389 | H9: -7612 | I9: -8794 | J9: -9231 | K9: -5602 | L9: -8648
B10: Cash from Investing Activity | C10: -14664 | D10: 4533 | E10: -632 | F10: -331 | G10: -7373 | H10: -6485 | I10: -1071 | J10: -5093 | K10: -1864 | L10: 3546
B11: Fixed assets purchased | C11: -2760 | D11: -1998 | E11: -2445 | F11: -3307 | G11: -2107 | H11: -2161 | I11: -2579 | J11: -2201 | K11: -2237 | L11: -2727
B12: Investments purchased | C12: -66410 | D12: -69159 | E12: -79410 | F12: -37482 | G12: -46738 | H12: -59951 | I12: -75800 | J12: -78092 | K12: -82742 | L12: -82617
B13: Investments sold | C13: 52048 | D13: 74003 | E13: 78098 | F13: 38861 | G13: 40381 | H13: 57356 | I13: 76722 | J13: 72930 | K13: 84877 | L13: 89699
B14: Interest received | C14: 0 | D14: 0 | E14: 0 | F14: 0 | G14: 0 | H14: 0 | I14: 0 | J14: 0 | K14: 0 | L14: 0
... B25: Net Cash Flow | C25: -10072 | D25: -2754 | E25: -303 | F25: -919 | G25: 6065 | H25: -7242 | I25: -5299 | J25: 2613 | K25: 9669 | L25: -2254

Sheet Financials>

Sheet HistoricalFS
B2: ="Historical Financial Statement - "&'Data Sheet'!B1 -> Historical Financial Statement - INFOSYS LTD
B3: Years | C3: ='Data Sheet'!B16 -> 42825 | D3: ='Data Sheet'!C16 -> 43190 | E3: ='Data Sheet'!D16 -> 43555 | F3: ='Data Sheet'!E16 -> 43921 | G3: ='Data Sheet'!F16 -> 44286 | H3: ='Data Sheet'!G16 -> 44651 | I3: ='Data Sheet'!H16 -> 45016 | J3: ='Data Sheet'!I16 -> 45382 | ... L3: ='Data Sheet'!K16 -> 46112 | M3: LTM
A5: # | B5: Income Statement
B6: Sales | C6: =IFERROR('Data Sheet'!B17,0) -> 68484 | D6: =IFERROR('Data Sheet'!C17,0) -> 70522 | E6: =IFERROR('Data Sheet'!D17,0) -> 82675 | F6: =IFERROR('Data Sheet'!E17,0) -> 90791 | G6: =IFERROR('Data Sheet'!F17,0) -> 100472 | H6: =IFERROR('Data Sheet'!G17,0) -> 121641 | I6: =IFERROR('Data Sheet'!H17,0) -> 146767 | J6: =IFERROR('Data Sheet'!I17,0) -> 153670 | ... L6: =IFERROR('Data Sheet'!K17,0) -> 178650 | M6: =IFERROR(SUM('Data Sheet'!H42:K42),0) -> 184582
B7: Sales Growth | C7: - | D7: =D6/C6-1 -> 0.029758776 | E7: =E6/D6-1 -> 0.1723292 | F7: =F6/E6-1 -> 0.098167523 | G7: =G6/F6-1 -> 0.10662951 | H7: =H6/G6-1 -> 0.21069552 | I7: =I6/H6-1 -> 0.20655864 | J7: =J6/I6-1 -> 0.047033734 | K7: =K6/J6-1 -> 0.060649444 | ... M7: =M6/L6-1 -> 0.03320459
B9: COGS | C9: =IFERROR(SUM('Data Sheet'!B18,'Data Sheet'!B20:B22)-1*'Data Sheet'!B19,0) -> 44609 | D9: =IFERROR(SUM('Data Sheet'!C18,'Data Sheet'!C20:C22)-1*'Data Sheet'!C19,0) -> 46395 | E9: =IFERROR(SUM('Data Sheet'!D18,'Data Sheet'!D20:D22)-1*'Data Sheet'!D19,0) -> 55446 | F9: =IFERROR(SUM('Data Sheet'!E18,'Data Sheet'!E20:E22)-1*'Data Sheet'!E19,0) -> 62210 | G9: =IFERROR(SUM('Data Sheet'!F18,'Data Sheet'!F20:F22)-1*'Data Sheet'!F19,0) -> 68490 | H9: =IFERROR(SUM('Data Sheet'!G18,'Data Sheet'!G20:G22)-1*'Data Sheet'!G19,0) -> 84819 | I9: =IFERROR(SUM('Data Sheet'!H18,'Data Sheet'!H20:H22)-1*'Data Sheet'!H19,0) -> 104880 | J9: =IFERROR(SUM('Data Sheet'!I18,'Data Sheet'!I20:I22)-1*'Data Sheet'!I19,0) -> 110030 | ... L9: =IFERROR(SUM('Data Sheet'!K18,'Data Sheet'!K20:K22)-1*'Data Sheet'!K19,0) -> 128257 | M9: =IFERROR(SUM('Data Sheet'!H43:K43),0) -> 140837
B10: COGS % Sales | C10: =C9/C6 -> 0.65137842 | D10: =D9/D6 -> 0.65787981 | E10: =E9/E6 -> 0.67065014 | F10: =F9/F6 -> 0.68520007 | G10: =G9/G6 -> 0.68168246 | H10: =H9/H6 -> 0.69728957 | I10: =I9/I6 -> 0.71460206 | J10: =J9/J6 -> 0.71601484 | ... M10: =M9/M6 -> 0.76300506
B12: Gross Profit | C12: =C6-C9 -> 23875 | D12: =D6-D9 -> 24127 | E12: =E6-E9 -> 27229 | F12: =F6-F9 -> 28581 | G12: =G6-G9 -> 31982 | H12: =H6-H9 -> 36822 | I12: =I6-I9 -> 41887 | J12: =J6-J9 -> 43640 | ... M12: =M6-M9 -> 43745
B13: Gross Margins | C13: =C12/C6 -> 0.34862158 | D13: =D12/D6 -> 0.34212019 | E13: =E12/E6 -> 0.32934986 | F13: =F12/F6 -> 0.31479993 | G13: =G12/G6 -> 0.31831754 | H13: =H12/H6 -> 0.30271043 | I13: =I12/I6 -> 0.28539794 | J13: =J12/J6 -> 0.28398516 | ... M13: =M12/M6 -> 0.23699494
B15: Selling & General Expenses | C15: =IFERROR(SUM('Data Sheet'!B23:B24),0) -> 5271 | D15: =IFERROR(SUM('Data Sheet'!C23:C24),0) -> 5305 | E15: =IFERROR(SUM('Data Sheet'!D23:D24),0) -> 7059 | F15: =IFERROR(SUM('Data Sheet'!E23:E24),0) -> 6314 | G15: =IFERROR(SUM('Data Sheet'!F23:F24),0) -> 4093 | H15: =IFERROR(SUM('Data Sheet'!G23:G24),0) -> 5331 | I15: =IFERROR(SUM('Data Sheet'!H23:H24),0) -> 6757 | J15: =IFERROR(SUM('Data Sheet'!I23:I24),0) -> 7215 | ... L15: =IFERROR(SUM('Data Sheet'!K23:K24),0) -> 8113
B16: S&G Exp % Sales | C16: =C15/C6 -> 0.076966883 | D16: =D15/D6 -> 0.075224753 | E16: =E15/E6 -> 0.085382522 | F16: =F15/F6 -> 0.069544338 | G16: =G15/G6 -> 0.040737718 | H16: =H15/H6 -> 0.043825684 | I16: =I15/I6 -> 0.04603896 | J16: =J15/J6 -> 0.046951259 | ... M16: =M15/M6 -> 0
B18: EBITDA | C18: =C12-C15 -> 18604 | D18: =D12-D15 -> 18822 | E18: =E12-E15 -> 20170 | F18: =F12-F15 -> 22267 | G18: =G12-G15 -> 27889 | H18: =H12-H15 -> 31491 | I18: =I12-I15 -> 35130 | J18: =J12-J15 -> 36425 | ... L18: =L12-L15 -> 42280 | M18: =IFERROR(SUM('Data Sheet'!H51:K51),0) -> 46683
B19: EBITDA Margins | C19: =C18/C6 -> 0.27165469 | D19: =D18/D6 -> 0.26689544 | E19: =E18/E6 -> 0.24396734 | F19: =F18/F6 -> 0.24525559 | G19: =G18/G6 -> 0.27757982 | H19: =H18/H6 -> 0.25888475 | I19: =I18/I6 -> 0.23935898 | J19: =J18/J6 -> 0.2370339 | ... M19: =M18/M6 -> 0.25291198
B21: Interest | C21: =IFERROR('Data Sheet'!B27,0) -> 0 | D21: =IFERROR('Data Sheet'!C27,0) -> 0 | E21: =IFERROR('Data Sheet'!D27,0) -> 0 | F21: =IFERROR('Data Sheet'!E27,0) -> 170 | G21: =IFERROR('Data Sheet'!F27,0) -> 195 | H21: =IFERROR('Data Sheet'!G27,0) -> 200 | I21: =IFERROR('Data Sheet'!H27,0) -> 284 | J21: =IFERROR('Data Sheet'!I27,0) -> 470 | ... L21: =IFERROR('Data Sheet'!K27,0) -> 416 | M21: =IFERROR(SUM('Data Sheet'!H46:K46),0) -> 430
B22: Interest % Sales | C22: =C21/C6 -> 0 | D22: =D21/D6 -> 0 | E22: =E21/E6 -> 0 | F22: =F21/F6 -> 0.0018724323 | G22: =G21/G6 -> 0.0019408392 | H22: =H21/H6 -> 0.0016441825 | I22: =I21/I6 -> 0.0019350399 | J22: =J21/J6 -> 0.003058502 | ... M22: =M21/M6 -> 0.0023295879
B24: Depreciation | C24: =IFERROR('Data Sheet'!B26,0) -> 1703 | D24: =IFERROR('Data Sheet'!C26,0) -> 1863 | E24: =IFERROR('Data Sheet'!D26,0) -> 2011 | F24: =IFERROR('Data Sheet'!E26,0) -> 2893 | G24: =IFERROR('Data Sheet'!F26,0) -> 3267 | H24: =IFERROR('Data Sheet'!G26,0) -> 3476 | I24: =IFERROR('Data Sheet'!H26,0) -> 4225 | J24: =IFERROR('Data Sheet'!I26,0) -> 4678 | ... L24: =IFERROR('Data Sheet'!K26,0) -> 4902 | M24: =IFERROR(SUM('Data Sheet'!H45:K45),0) -> 5007
B25: Depreciation%Sales | C25: =C24/C6 -> 0.024867122 | D25: =D24/D6 -> 0.026417288 | E25: =E24/E6 -> 0.024324161 | F25: =F24/F6 -> 0.031864392 | G25: =G24/G6 -> 0.032516522 | H25: =H24/H6 -> 0.028575891 | I25: =I24/I6 -> 0.028787125 | J25: =J24/J6 -> 0.030441856 | ... M25: =M24/M6 -> 0.027126155
B27: Earnings Before Tax | C27: =IFERROR(C18-SUM(C24,C21),0) -> 16901 | D27: =IFERROR(D18-SUM(D24,D21),0) -> 16959 | E27: =IFERROR(E18-SUM(E24,E21),0) -> 18159 | F27: =IFERROR(F18-SUM(F24,F21),0) -> 19204 | G27: =IFERROR(G18-SUM(G24,G21),0) -> 24427 | H27: =IFERROR(H18-SUM(H24,H21),0) -> 27815 | I27: =IFERROR(I18-SUM(I24,I21),0) -> 30621 | J27: =IFERROR(J18-SUM(J24,J21),0) -> 31277 | ... M27: =IFERROR(M18-SUM(M24,M21),0) -> 41246
B28: EBT % Sales | C28: =C27/C6 -> 0.24678757 | D28: =D27/D6 -> 0.24047815 | E28: =E27/E6 -> 0.21964318 | F28: =F27/F6 -> 0.21151876 | G28: =G27/G6 -> 0.24312246 | H28: =H27/H6 -> 0.22866468 | I28: =I27/I6 -> 0.20863682 | J28: =J27/J6 -> 0.20353355 | ... M28: =M27/M6 -> 0.22345624
B30: Tax | C30: =IFERROR('Data Sheet'!B29,0) -> 5598 | D30: =IFERROR('Data Sheet'!C29,0) -> 4241 | E30: =IFERROR('Data Sheet'!D29,0) -> 5631 | F30: =IFERROR('Data Sheet'!E29,0) -> 5368 | G30: =IFERROR('Data Sheet'!F29,0) -> 7205 | H30: =IFERROR('Data Sheet'!G29,0) -> 7964 | I30: =IFERROR('Data Sheet'!H29,0) -> 9214 | J30: =IFERROR('Data Sheet'!I29,0) -> 9740 | ... L30: =IFERROR('Data Sheet'!K29,0) -> 10521 | M30: =IFERROR(SUM('Data Sheet'!H48:K48),0) -> 10958
B31: Effective Tax Rate | C31: =C30/C27 -> 0.331223 | D31: =D30/D27 -> 0.25007371 | E31: =E30/E27 -> 0.31009417 | F31: =F30/F27 -> 0.2795251 | G31: =G30/G27 -> 0.29496049 | H31: =H30/H27 -> 0.28632033 | I31: =I30/I27 -> 0.30090461 | J31: =J30/J27 -> 0.31141094 | ... M31: =M30/M27 -> 0.26567425
B33: Net Profit | C33: =IFERROR(C27-C30,0) -> 11303 | D33: =IFERROR(D27-D30,0) -> 12718 | E33: =IFERROR(E27-E30,0) -> 12528 | F33: =IFERROR(F27-F30,0) -> 13836 | G33: =IFERROR(G27-G30,0) -> 17222 | H33: =IFERROR(H27-H30,0) -> 19851 | I33: =IFERROR(I27-I30,0) -> 21407 | J33: =IFERROR(J27-J30,0) -> 21537 | ... M33: =IFERROR(M27-M30,0) -> 30288
B34: Net Margins | C34: =C33/C6 -> 0.16504585 | D34: =D33/D6 -> 0.18034089 | E34: =E33/E6 -> 0.15153311 | F34: =F33/F6 -> 0.15239396 | G34: =G33/G6 -> 0.17141094 | H34: =H33/H6 -> 0.16319333 | I34: =I33/I6 -> 0.14585704 | J34: =J33/J6 -> 0.14015097 | ... M34: =M33/M6 -> 0.16408967
B36: No of Equity Shares | C36: =IFERROR('Data Sheet'!B93,0) -> 459.39 | D36: =IFERROR('Data Sheet'!C93,0) -> 436.82 | E36: =IFERROR('Data Sheet'!D93,0) -> 436.89 | F36: =IFERROR('Data Sheet'!E93,0) -> 425.9 | G36: =IFERROR('Data Sheet'!F93,0) -> 426.07 | H36: =IFERROR('Data Sheet'!G93,0) -> 420.67 | I36: =IFERROR('Data Sheet'!H93,0) -> 414.86 | J36: =IFERROR('Data Sheet'!I93,0) -> 415.09 | ... L36: =IFERROR('Data Sheet'!K93,0) -> 405.56 | M36: =L36 -> 405.56
B38: Earnings per Share | C38: =IFERROR(C33/C36,0) -> 24.604367 | D38: =IFERROR(D33/D36,0) -> 29.114967 | E38: =IFERROR(E33/E36,0) -> 28.67541 | F38: =IFERROR(F33/F36,0) -> 32.486499 | G38: =IFERROR(G33/G36,0) -> 40.420588 | H38: =IFERROR(H33/H36,0) -> 47.189008 | I38: =IFERROR(I33/I36,0) -> 51.60054 | J38: =IFERROR(J33/J36,0) -> 51.885133 | ... M38: =IFERROR(M33/M36,0) -> 74.681921
B39: EPS Growth % | D39: =IFERROR(D38/C38-1,0) -> 0.18332521 | E39: =IFERROR(E38/D38-1,0) -> -0.015097286 | F39: =IFERROR(F38/E38-1,0) -> 0.13290442 | G39: =IFERROR(G38/F38-1,0) -> 0.24422727 | H39: =IFERROR(H38/G38-1,0) -> 0.16744981 | I39: =IFERROR(I38/H38-1,0) -> 0.093486431 | J39: =IFERROR(J38/I38-1,0) -> 0.0055153183 | K39: =IFERROR(K38/J38-1,0) -> 0.074273236 | ... M39: =IFERROR(M38/L38-1,0) -> 0.14549374
B41: Dividend per Share | C41: =IFERROR('Data Sheet'!B31/HistoricalFS!C36,0) -> 12.824833 | D41: =IFERROR('Data Sheet'!C31/HistoricalFS!D36,0) -> 21.669337 | E41: =IFERROR('Data Sheet'!D31/HistoricalFS!E36,0) -> 21.109433 | F41: =IFERROR('Data Sheet'!E31/HistoricalFS!F36,0) -> 17.438366 | G41: =IFERROR('Data Sheet'!F31/HistoricalFS!G36,0) -> 26.91952 | H41: =IFERROR('Data Sheet'!G31/HistoricalFS!H36,0) -> 30.92115 | I41: =IFERROR('Data Sheet'!H31/HistoricalFS!I36,0) -> 33.913127 | J41: =IFERROR('Data Sheet'!I31/HistoricalFS!J36,0) -> 45.901371 | ... M41: =IFERROR('Data Sheet'!L31/HistoricalFS!M36,0) -> 0
B42: Dividend payout ratio | C42: =IFERROR(C41/C38,0) -> 0.52124215 | D42: =IFERROR(D41/D38,0) -> 0.74426797 | E42: =IFERROR(E41/E38,0) -> 0.73615102 | F42: =IFERROR(F41/F38,0) -> 0.53678809 | G42: =IFERROR(G41/G38,0) -> 0.66598537 | H42: =IFERROR(H41/H38,0) -> 0.6552617 | I42: =IFERROR(I41/I38,0) -> 0.65722427 | J42: =IFERROR(J41/J38,0) -> 0.88467289 | ... M42: =IFERROR(M41/M38,0) -> 0
B44: Retained Earnings | C44: =IFERROR(IF(C38>C41,1-C42,0),0) -> 0.47875785 | D44: =IFERROR(IF(D38>D41,1-D42,0),0) -> 0.25573203 | E44: =IFERROR(IF(E38>E41,1-E42,0),0) -> 0.26384898 | F44: =IFERROR(IF(F38>F41,1-F42,0),0) -> 0.46321191 | G44: =IFERROR(IF(G38>G41,1-G42,0),0) -> 0.33401463 | H44: =IFERROR(IF(H38>H41,1-H42,0),0) -> 0.3447383 | I44: =IFERROR(IF(I38>I41,1-I42,0),0) -> 0.34277573 | J44: =IFERROR(IF(J38>J41,1-J42,0),0) -> 0.11532711 | ... M44: =IFERROR(IF(M38>M41,1-M42,0),0) -> 1
A46: # | B46: Balance Sheet
B47: Equity Share Capital | C47: =IFERROR('Data Sheet'!B57,0) -> 1144 | D47: =IFERROR('Data Sheet'!C57,0) -> 1088 | E47: =IFERROR('Data Sheet'!D57,0) -> 2170 | F47: =IFERROR('Data Sheet'!E57,0) -> 2122 | G47: =IFERROR('Data Sheet'!F57,0) -> 2124 | H47: =IFERROR('Data Sheet'!G57,0) -> 2098 | I47: =IFERROR('Data Sheet'!H57,0) -> 2069 | J47: =IFERROR('Data Sheet'!I57,0) -> 2071 | ... L47: =IFERROR('Data Sheet'!K57,0) -> 2024
B48: Reserves | C48: =IFERROR('Data Sheet'!B58,0) -> 67838 | D48: =IFERROR('Data Sheet'!C58,0) -> 63835 | E48: =IFERROR('Data Sheet'!D58,0) -> 62778 | F48: =IFERROR('Data Sheet'!E58,0) -> 63328 | G48: =IFERROR('Data Sheet'!F58,0) -> 74227 | H48: =IFERROR('Data Sheet'!G58,0) -> 73252 | I48: =IFERROR('Data Sheet'!H58,0) -> 73338 | J48: =IFERROR('Data Sheet'!I58,0) -> 86045 | ... L48: =IFERROR('Data Sheet'!K58,0) -> 90828
B49: Borrowings | C49: =IFERROR('Data Sheet'!B59,0) -> 0 | D49: =IFERROR('Data Sheet'!C59,0) -> 0 | E49: =IFERROR('Data Sheet'!D59,0) -> 0 | F49: =IFERROR('Data Sheet'!E59,0) -> 4633 | G49: =IFERROR('Data Sheet'!F59,0) -> 5325 | H49: =IFERROR('Data Sheet'!G59,0) -> 5474 | I49: =IFERROR('Data Sheet'!H59,0) -> 8299 | J49: =IFERROR('Data Sheet'!I59,0) -> 8359 | ... L49: =IFERROR('Data Sheet'!K59,0) -> 9176
B50: Other Liabilities | C50: =IFERROR('Data Sheet'!B60,0) -> 14166 | D50: =IFERROR('Data Sheet'!C60,0) -> 14426 | E50: =IFERROR('Data Sheet'!D60,0) -> 19118 | F50: =IFERROR('Data Sheet'!E60,0) -> 21717 | G50: =IFERROR('Data Sheet'!F60,0) -> 25835 | H50: =IFERROR('Data Sheet'!G60,0) -> 35905 | I50: =IFERROR('Data Sheet'!H60,0) -> 40890 | J50: =IFERROR('Data Sheet'!I60,0) -> 39545 | ... L50: =IFERROR('Data Sheet'!K60,0) -> 52260
B51: Total Liabilities | C51: =IFERROR('Data Sheet'!B61,0) -> 83148 | D51: =IFERROR('Data Sheet'!C61,0) -> 79349 | E51: =IFERROR('Data Sheet'!D61,0) -> 84066 | F51: =IFERROR('Data Sheet'!E61,0) -> 91800 | G51: =IFERROR('Data Sheet'!F61,0) -> 107511 | H51: =IFERROR('Data Sheet'!G61,0) -> 116729 | I51: =IFERROR('Data Sheet'!H61,0) -> 124596 | J51: =IFERROR('Data Sheet'!I61,0) -> 136020 | ... L51: =IFERROR('Data Sheet'!K61,0) -> 154288
B53: Fixed Assets Net Block | C53: =IFERROR('Data Sheet'!B62,0) -> 14179 | D53: =IFERROR('Data Sheet'!C62,0) -> 12574 | E53: =IFERROR('Data Sheet'!D62,0) -> 15710 | F53: =IFERROR('Data Sheet'!E62,0) -> 23789 | G53: =IFERROR('Data Sheet'!F62,0) -> 25505 | H53: =IFERROR('Data Sheet'!G62,0) -> 25800 | I53: =IFERROR('Data Sheet'!H62,0) -> 29225 | J53: =IFERROR('Data Sheet'!I62,0) -> 27622 | ... L53: =IFERROR('Data Sheet'!K62,0) -> 33770
B54: Capital Work in Progress | C54: =IFERROR('Data Sheet'!B63,0) -> 1365 | D54: =IFERROR('Data Sheet'!C63,0) -> 1606 | E54: =IFERROR('Data Sheet'!D63,0) -> 1388 | F54: =IFERROR('Data Sheet'!E63,0) -> 954 | G54: =IFERROR('Data Sheet'!F63,0) -> 922 | H54: =IFERROR('Data Sheet'!G63,0) -> 416 | I54: =IFERROR('Data Sheet'!H63,0) -> 288 | J54: =IFERROR('Data Sheet'!I63,0) -> 293 | ... L54: =IFERROR('Data Sheet'!K63,0) -> 526
B55: Investments | C55: =IFERROR('Data Sheet'!B64,0) -> 16423 | D55: =IFERROR('Data Sheet'!C64,0) -> 12163 | E55: =IFERROR('Data Sheet'!D64,0) -> 11261 | F55: =IFERROR('Data Sheet'!E64,0) -> 8792 | G55: =IFERROR('Data Sheet'!F64,0) -> 14205 | H55: =IFERROR('Data Sheet'!G64,0) -> 20324 | I55: =IFERROR('Data Sheet'!H64,0) -> 19478 | J55: =IFERROR('Data Sheet'!I64,0) -> 24623 | ... L55: =IFERROR('Data Sheet'!K64,0) -> 21880
B56: Other Assets | C56: =IFERROR('Data Sheet'!B65-SUM('Data Sheet'!B67:B69),0) -> 16234 | D56: =IFERROR('Data Sheet'!C65-SUM('Data Sheet'!C67:C69),0) -> 20046 | E56: =IFERROR('Data Sheet'!D65-SUM('Data Sheet'!D67:D69),0) -> 21312 | F56: =IFERROR('Data Sheet'!E65-SUM('Data Sheet'!E67:E69),0) -> 21129 | G56: =IFERROR('Data Sheet'!F65-SUM('Data Sheet'!F67:F69),0) -> 22871 | H56: =IFERROR('Data Sheet'!G65-SUM('Data Sheet'!G67:G69),0) -> 30019 | I56: =IFERROR('Data Sheet'!H65-SUM('Data Sheet'!H67:H69),0) -> 38008 | J56: =IFERROR('Data Sheet'!I65-SUM('Data Sheet'!I67:I69),0) -> 38503 | ... L56: =IFERROR('Data Sheet'!K65-SUM('Data Sheet'!K67:K69),0) -> 40677
B57: Total Non Current Assets | C57: =SUM(C53:C56) -> 48201 | D57: =SUM(D53:D56) -> 46389 | E57: =SUM(E53:E56) -> 49671 | F57: =SUM(F53:F56) -> 54664 | G57: =SUM(G53:G56) -> 63503 | H57: =SUM(H53:H56) -> 76559 | I57: =SUM(I53:I56) -> 86999 | J57: =SUM(J53:J56) -> 91041 | ... L57: =SUM(L53:L56) -> 96853
B59: Receivables | C59: =IFERROR('Data Sheet'!B67,0) -> 12322 | D59: =IFERROR('Data Sheet'!C67,0) -> 13142 | E59: =IFERROR('Data Sheet'!D67,0) -> 14827 | F59: =IFERROR('Data Sheet'!E67,0) -> 18487 | G59: =IFERROR('Data Sheet'!F67,0) -> 19294 | H59: =IFERROR('Data Sheet'!G67,0) -> 22698 | I59: =IFERROR('Data Sheet'!H67,0) -> 25424 | J59: =IFERROR('Data Sheet'!I67,0) -> 30193 | ... L59: =IFERROR('Data Sheet'!K67,0) -> 35234
B60: Inventory | C60: =IFERROR('Data Sheet'!B68,0) -> 0 | D60: =IFERROR('Data Sheet'!C68,0) -> 0 | E60: =IFERROR('Data Sheet'!D68,0) -> 0 | F60: =IFERROR('Data Sheet'!E68,0) -> 0 | G60: =IFERROR('Data Sheet'!F68,0) -> 0 | H60: =IFERROR('Data Sheet'!G68,0) -> 0 | I60: =IFERROR('Data Sheet'!H68,0) -> 0 | J60: =IFERROR('Data Sheet'!I68,0) -> 0 | ... L60: =IFERROR('Data Sheet'!K68,0) -> 0
B61: Cash & Bank | C61: =IFERROR('Data Sheet'!B69,0) -> 22625 | D61: =IFERROR('Data Sheet'!C69,0) -> 19818 | E61: =IFERROR('Data Sheet'!D69,0) -> 19568 | F61: =IFERROR('Data Sheet'!E69,0) -> 18649 | G61: =IFERROR('Data Sheet'!F69,0) -> 24714 | H61: =IFERROR('Data Sheet'!G69,0) -> 17472 | I61: =IFERROR('Data Sheet'!H69,0) -> 12173 | J61: =IFERROR('Data Sheet'!I69,0) -> 14786 | ... L61: =IFERROR('Data Sheet'!K69,0) -> 22201
B62: Total Current Assets | C62: =IFERROR(SUM(C59:C61),0) -> 34947 | D62: =IFERROR(SUM(D59:D61),0) -> 32960 | E62: =IFERROR(SUM(E59:E61),0) -> 34395 | F62: =IFERROR(SUM(F59:F61),0) -> 37136 | G62: =IFERROR(SUM(G59:G61),0) -> 44008 | H62: =IFERROR(SUM(H59:H61),0) -> 40170 | I62: =IFERROR(SUM(I59:I61),0) -> 37597 | J62: =IFERROR(SUM(J59:J61),0) -> 44979 | ... L62: =IFERROR(SUM(L59:L61),0) -> 57435
B64: Total Assets | C64: =IFERROR(C62+C57,0) -> 83148 | D64: =IFERROR(D62+D57,0) -> 79349 | E64: =IFERROR(E62+E57,0) -> 84066 | F64: =IFERROR(F62+F57,0) -> 91800 | G64: =IFERROR(G62+G57,0) -> 107511 | H64: =IFERROR(H62+H57,0) -> 116729 | I64: =IFERROR(I62+I57,0) -> 124596 | J64: =IFERROR(J62+J57,0) -> 136020 | ... L64: =IFERROR(L62+L57,0) -> 154288
B66: Check | C66: =C64=C51 -> TRUE | D66: =D64=D51 -> TRUE | E66: =E64=E51 -> TRUE | F66: =F64=F51 -> TRUE | G66: =G64=G51 -> TRUE | H66: =H64=H51 -> TRUE | I66: =I64=I51 -> TRUE | J66: =J64=J51 -> TRUE | ... L66: =L64=L51 -> TRUE
A68: # | B68: Cash Flow Statements
B69: Operating Activities
B70: Profit from operations | C70: =IFERROR('Cash Flow Data'!C4,0) -> 19340 | D70: =IFERROR('Cash Flow Data'!D4,0) -> 19963 | E70: =IFERROR('Cash Flow Data'!E4,0) -> 22126 | F70: =IFERROR('Cash Flow Data'!F4,0) -> 23920 | G70: =IFERROR('Cash Flow Data'!G4,0) -> 28845 | H70: =IFERROR('Cash Flow Data'!H4,0) -> 32921 | I70: =IFERROR('Cash Flow Data'!I4,0) -> 37605 | J70: =IFERROR('Cash Flow Data'!J4,0) -> 39523 | ... L70: =IFERROR('Cash Flow Data'!L4,0) -> 45273
B71: Receivables | C71: =IFERROR('Cash Flow Data'!C5,0) -> -1743 | D71: =IFERROR('Cash Flow Data'!D5,0) -> -1523 | E71: =IFERROR('Cash Flow Data'!E5,0) -> -2881 | F71: =IFERROR('Cash Flow Data'!F5,0) -> -3861 | G71: =IFERROR('Cash Flow Data'!G5,0) -> -1835 | H71: =IFERROR('Cash Flow Data'!H5,0) -> -7937 | I71: =IFERROR('Cash Flow Data'!I5,0) -> -7076 | J71: =IFERROR('Cash Flow Data'!J5,0) -> -2667 | ... L71: =IFERROR('Cash Flow Data'!L5,0) -> -5177
B72: Payables | C72: =IFERROR('Cash Flow Data'!C6,0) -> -19 | D72: =IFERROR('Cash Flow Data'!D6,0) -> 328 | E72: =IFERROR('Cash Flow Data'!E6,0) -> 916 | F72: =IFERROR('Cash Flow Data'!F6,0) -> -373 | G72: =IFERROR('Cash Flow Data'!G6,0) -> -245 | H72: =IFERROR('Cash Flow Data'!H6,0) -> 1489 | I72: =IFERROR('Cash Flow Data'!I6,0) -> -279 | J72: =IFERROR('Cash Flow Data'!J6,0) -> 91 | ... L72: =IFERROR('Cash Flow Data'!L6,0) -> -26
B73: Loans Advances | C73: =IFERROR('Cash Flow Data'!C7,0) -> 0 | D73: =IFERROR('Cash Flow Data'!D7,0) -> 0 | E73: =IFERROR('Cash Flow Data'!E7,0) -> 0 | F73: =IFERROR('Cash Flow Data'!F7,0) -> 0 | G73: =IFERROR('Cash Flow Data'!G7,0) -> -534 | H73: =IFERROR('Cash Flow Data'!H7,0) -> -1914 | I73: =IFERROR('Cash Flow Data'!I7,0) -> -3108 | J73: =IFERROR('Cash Flow Data'!J7,0) -> -1172 | ... L73: =IFERROR('Cash Flow Data'!L7,0) -> -2645
B74: Other WC items | C74: =IFERROR('Cash Flow Data'!C8,0) -> -394 | D74: =IFERROR('Cash Flow Data'!D8,0) -> 1279 | E74: =IFERROR('Cash Flow Data'!E8,0) -> 1512 | F74: =IFERROR('Cash Flow Data'!F8,0) -> 1867 | G74: =IFERROR('Cash Flow Data'!G8,0) -> 3382 | H74: =IFERROR('Cash Flow Data'!H8,0) -> 6938 | I74: =IFERROR('Cash Flow Data'!I8,0) -> 4119 | J74: =IFERROR('Cash Flow Data'!J8,0) -> -1334 | ... L74: =IFERROR('Cash Flow Data'!L8,0) -> 5209
B75: Direct taxes | C75: =IFERROR('Cash Flow Data'!C9,0) -> -5653 | D75: =IFERROR('Cash Flow Data'!D9,0) -> -6829 | E75: =IFERROR('Cash Flow Data'!E9,0) -> -6832 | F75: =IFERROR('Cash Flow Data'!F9,0) -> -4550 | G75: =IFERROR('Cash Flow Data'!G9,0) -> -6389 | H75: =IFERROR('Cash Flow Data'!H9,0) -> -7612 | I75: =IFERROR('Cash Flow Data'!I9,0) -> -8794 | J75: =IFERROR('Cash Flow Data'!J9,0) -> -9231 | ... L75: =IFERROR('Cash Flow Data'!L9,0) -> -8648
B76: Cash from Operating Activities | C76: =SUM(C70:C75) -> 11531 | D76: =SUM(D70:D75) -> 13218 | E76: =SUM(E70:E75) -> 14841 | F76: =SUM(F70:F75) -> 17003 | G76: =SUM(G70:G75) -> 23224 | H76: =SUM(H70:H75) -> 23885 | I76: =SUM(I70:I75) -> 22467 | J76: =SUM(J70:J75) -> 25210 | ... L76: =SUM(L70:L75) -> 33986
B78: Investing Activities
B79: Fixed assets purchased | C79: =IFERROR('Cash Flow Data'!C11,0) -> -2760 | D79: =IFERROR('Cash Flow Data'!D11,0) -> -1998 | E79: =IFERROR('Cash Flow Data'!E11,0) -> -2445 | F79: =IFERROR('Cash Flow Data'!F11,0) -> -3307 | G79: =IFERROR('Cash Flow Data'!G11,0) -> -2107 | H79: =IFERROR('Cash Flow Data'!H11,0) -> -2161 | I79: =IFERROR('Cash Flow Data'!I11,0) -> -2579 | J79: =IFERROR('Cash Flow Data'!J11,0) -> -2201 | ... L79: =IFERROR('Cash Flow Data'!L11,0) -> -2727
B80: Investments purchased | C80: =IFERROR('Cash Flow Data'!C12,0) -> -66410 | D80: =IFERROR('Cash Flow Data'!D12,0) -> -69159 | E80: =IFERROR('Cash Flow Data'!E12,0) -> -79410 | F80: =IFERROR('Cash Flow Data'!F12,0) -> -37482 | G80: =IFERROR('Cash Flow Data'!G12,0) -> -46738 | H80: =IFERROR('Cash Flow Data'!H12,0) -> -59951 | I80: =IFERROR('Cash Flow Data'!I12,0) -> -75800 | J80: =IFERROR('Cash Flow Data'!J12,0) -> -78092 | ... L80: =IFERROR('Cash Flow Data'!L12,0) -> -82617
B81: Investments sold | C81: =IFERROR('Cash Flow Data'!C13,0) -> 52048 | D81: =IFERROR('Cash Flow Data'!D13,0) -> 74003 | E81: =IFERROR('Cash Flow Data'!E13,0) -> 78098 | F81: =IFERROR('Cash Flow Data'!F13,0) -> 38861 | G81: =IFERROR('Cash Flow Data'!G13,0) -> 40381 | H81: =IFERROR('Cash Flow Data'!H13,0) -> 57356 | I81: =IFERROR('Cash Flow Data'!I13,0) -> 76722 | J81: =IFERROR('Cash Flow Data'!J13,0) -> 72930 | ... L81: =IFERROR('Cash Flow Data'!L13,0) -> 89699
B82: Interest received | C82: =IFERROR('Cash Flow Data'!C14,0) -> 0 | D82: =IFERROR('Cash Flow Data'!D14,0) -> 0 | E82: =IFERROR('Cash Flow Data'!E14,0) -> 0 | F82: =IFERROR('Cash Flow Data'!F14,0) -> 0 | G82: =IFERROR('Cash Flow Data'!G14,0) -> 0 | H82: =IFERROR('Cash Flow Data'!H14,0) -> 0 | I82: =IFERROR('Cash Flow Data'!I14,0) -> 0 | J82: =IFERROR('Cash Flow Data'!J14,0) -> 0 | ... L82: =IFERROR('Cash Flow Data'!L14,0) -> 0
B83: Dividends received | C83: =IFERROR('Cash Flow Data'!C15,0) -> 2753 | D83: =IFERROR('Cash Flow Data'!D15,0) -> 1768 | E83: =IFERROR('Cash Flow Data'!E15,0) -> 1557 | F83: =IFERROR('Cash Flow Data'!F15,0) -> 1929 | G83: =IFERROR('Cash Flow Data'!G15,0) -> 1418 | H83: =IFERROR('Cash Flow Data'!H15,0) -> 1898 | I83: =IFERROR('Cash Flow Data'!I15,0) -> 1525 | J83: =IFERROR('Cash Flow Data'!J15,0) -> 1768 | ... L83: =IFERROR('Cash Flow Data'!L15,0) -> 2713
B84: Acquisition of companies | C84: =IFERROR('Cash Flow Data'!C16,0) -> 0 | D84: =IFERROR('Cash Flow Data'!D16,0) -> 0 | E84: =IFERROR('Cash Flow Data'!E16,0) -> 0 | F84: =IFERROR('Cash Flow Data'!F16,0) -> 0 | G84: =IFERROR('Cash Flow Data'!G16,0) -> 0 | H84: =IFERROR('Cash Flow Data'!H16,0) -> 0 | I84: =IFERROR('Cash Flow Data'!I16,0) -> 0 | J84: =IFERROR('Cash Flow Data'!J16,0) -> 0 | ... L84: =IFERROR('Cash Flow Data'!L16,0) -> 0
B85: Inter corporate deposits | C85: =IFERROR('Cash Flow Data'!C17,0) -> -164 | D85: =IFERROR('Cash Flow Data'!D17,0) -> -130 | E85: =IFERROR('Cash Flow Data'!E17,0) -> -24 | F85: =IFERROR('Cash Flow Data'!F17,0) -> -108 | G85: =IFERROR('Cash Flow Data'!G17,0) -> 0 | H85: =IFERROR('Cash Flow Data'!H17,0) -> 0 | I85: =IFERROR('Cash Flow Data'!I17,0) -> 0 | J85: =IFERROR('Cash Flow Data'!J17,0) -> 0 | ... L85: =IFERROR('Cash Flow Data'!L17,0) -> 0
B86: Other investing items | C86: =IFERROR('Cash Flow Data'!C18,0) -> -131 | D86: =IFERROR('Cash Flow Data'!D18,0) -> 49 | E86: =IFERROR('Cash Flow Data'!E18,0) -> 1592 | F86: =IFERROR('Cash Flow Data'!F18,0) -> -224 | G86: =IFERROR('Cash Flow Data'!G18,0) -> -327 | H86: =IFERROR('Cash Flow Data'!H18,0) -> -3627 | I86: =IFERROR('Cash Flow Data'!I18,0) -> -939 | J86: =IFERROR('Cash Flow Data'!J18,0) -> 502 | ... L86: =IFERROR('Cash Flow Data'!L18,0) -> -3522
B87: Cash from Investing Activities | C87: =SUM(C79:C86) -> -14664 | D87: =SUM(D79:D86) -> 4533 | E87: =SUM(E79:E86) -> -632 | F87: =SUM(F79:F86) -> -331 | G87: =SUM(G79:G86) -> -7373 | H87: =SUM(H79:H86) -> -6485 | I87: =SUM(I79:I86) -> -1071 | J87: =SUM(J79:J86) -> -5093 | ... L87: =SUM(L79:L86) -> 3546
B89: Financing Activities
B90: Proceeds from shares | C90: =IFERROR('Cash Flow Data'!C20,0) -> 0 | D90: =IFERROR('Cash Flow Data'!D20,0) -> 5 | E90: =IFERROR('Cash Flow Data'!E20,0) -> 6 | F90: =IFERROR('Cash Flow Data'!F20,0) -> 6 | G90: =IFERROR('Cash Flow Data'!G20,0) -> 15 | H90: =IFERROR('Cash Flow Data'!H20,0) -> 21 | I90: =IFERROR('Cash Flow Data'!I20,0) -> 35 | J90: =IFERROR('Cash Flow Data'!J20,0) -> 5 | ... L90: =IFERROR('Cash Flow Data'!L20,0) -> 2
B91: Repayment of borrowings | C91: =IFERROR('Cash Flow Data'!C21,0) -> 0 | D91: =IFERROR('Cash Flow Data'!D21,0) -> 0 | E91: =IFERROR('Cash Flow Data'!E21,0) -> 0 | F91: =IFERROR('Cash Flow Data'!F21,0) -> 0 | G91: =IFERROR('Cash Flow Data'!G21,0) -> 0 | H91: =IFERROR('Cash Flow Data'!H21,0) -> 0 | I91: =IFERROR('Cash Flow Data'!I21,0) -> 0 | J91: =IFERROR('Cash Flow Data'!J21,0) -> 0 | ... L91: =IFERROR('Cash Flow Data'!L21,0) -> 0
B92: Dividends paid | C92: =IFERROR('Cash Flow Data'!C22,0) -> -6939 | D92: =IFERROR('Cash Flow Data'!D22,0) -> -7464 | E92: =IFERROR('Cash Flow Data'!E22,0) -> -13705 | F92: =IFERROR('Cash Flow Data'!F22,0) -> -9548 | G92: =IFERROR('Cash Flow Data'!G22,0) -> -9137 | H92: =IFERROR('Cash Flow Data'!H22,0) -> -12731 | I92: =IFERROR('Cash Flow Data'!I22,0) -> -13653 | J92: =IFERROR('Cash Flow Data'!J22,0) -> -14731 | ... L92: =IFERROR('Cash Flow Data'!L22,0) -> -18656
B93: Financial liabilities | C93: =IFERROR('Cash Flow Data'!C23,0) -> 0 | D93: =IFERROR('Cash Flow Data'!D23,0) -> 0 | E93: =IFERROR('Cash Flow Data'!E23,0) -> 0 | F93: =IFERROR('Cash Flow Data'!F23,0) -> -571 | G93: =IFERROR('Cash Flow Data'!G23,0) -> -698 | H93: =IFERROR('Cash Flow Data'!H23,0) -> -915 | I93: =IFERROR('Cash Flow Data'!I23,0) -> -1231 | J93: =IFERROR('Cash Flow Data'!J23,0) -> -2024 | ... L93: =IFERROR('Cash Flow Data'!L23,0) -> -2824
B94: Other financing items | C94: =IFERROR('Cash Flow Data'!C24,0) -> 0 | D94: =IFERROR('Cash Flow Data'!D24,0) -> -13046 | E94: =IFERROR('Cash Flow Data'!E24,0) -> -813 | F94: =IFERROR('Cash Flow Data'!F24,0) -> -7478 | G94: =IFERROR('Cash Flow Data'!G24,0) -> 34 | H94: =IFERROR('Cash Flow Data'!H24,0) -> -11017 | I94: =IFERROR('Cash Flow Data'!I24,0) -> -11846 | J94: =IFERROR('Cash Flow Data'!J24,0) -> -754 | ... L94: =IFERROR('Cash Flow Data'!L24,0) -> -18308
B95: Cash from Financing Activities | C95: =SUM(C90:C94) -> -6939 | D95: =SUM(D90:D94) -> -20505 | E95: =SUM(E90:E94) -> -14512 | F95: =SUM(F90:F94) -> -17591 | G95: =SUM(G90:G94) -> -9786 | H95: =SUM(H90:H94) -> -24642 | I95: =SUM(I90:I94) -> -26695 | J95: =SUM(J90:J94) -> -17504 | ... L95: =SUM(L90:L94) -> -39786
B97: Net Cash Flow | C97: =IFERROR(C76+C87+C95,0) -> -10072 | D97: =IFERROR(D76+D87+D95,0) -> -2754 | E97: =IFERROR(E76+E87+E95,0) -> -303 | F97: =IFERROR(F76+F87+F95,0) -> -919 | G97: =IFERROR(G76+G87+G95,0) -> 6065 | H97: =IFERROR(H76+H87+H95,0) -> -7242 | I97: =IFERROR(I76+I87+I95,0) -> -5299 | J97: =IFERROR(J76+J87+J95,0) -> 2613 | ... L97: =IFERROR(L76+L87+L95,0) -> -2254

Sheet Ratio Analysis
G2: ="Ratio Analysis - "& 'Data Sheet'!B1 -> Ratio Analysis - INFOSYS LTD
B3: Years | D3: 42811 | E3: 43177 | F3: 43543 | G3: 43909 | H3: 44275 | I3: 44641 | J3: 45007 | K3: 45373 | L3: 45739 | M3: 46105 | O3: MEAN | P3: MEDIAN
B5: SalesGrowth | E5: =IFERROR(HistoricalFS!D7,0) -> 0.029758776 | F5: =IFERROR(HistoricalFS!E7,0) -> 0.1723292 | G5: =IFERROR(HistoricalFS!F7,0) -> 0.098167523 | H5: =IFERROR(HistoricalFS!G7,0) -> 0.10662951 | I5: =IFERROR(HistoricalFS!H7,0) -> 0.21069552 | J5: =IFERROR(HistoricalFS!I7,0) -> 0.20655864 | K5: =IFERROR(HistoricalFS!J7,0) -> 0.047033734 | L5: =IFERROR(HistoricalFS!K7,0) -> 0.060649444 | M5: =IFERROR(HistoricalFS!L7,0) -> 0.096079514 | O5: =IFERROR(AVERAGE(E5:M5),0) -> 0.11421132 | P5: =IFERROR(MEDIAN(E5:M5),0) -> 0.098167523
B6: EBITDA Growth | E6: =IFERROR(HistoricalFS!D18/HistoricalFS!C18-1,0) -> 0.01171791 | F6: =IFERROR(HistoricalFS!E18/HistoricalFS!D18-1,0) -> 0.071618319 | G6: =IFERROR(HistoricalFS!F18/HistoricalFS!E18-1,0) -> 0.10396629 | H6: =IFERROR(HistoricalFS!G18/HistoricalFS!F18-1,0) -> 0.25248125 | I6: =IFERROR(HistoricalFS!H18/HistoricalFS!G18-1,0) -> 0.12915486 | J6: =IFERROR(HistoricalFS!I18/HistoricalFS!H18-1,0) -> 0.11555683 | K6: =IFERROR(HistoricalFS!J18/HistoricalFS!I18-1,0) -> 0.03686308 | L6: =IFERROR(HistoricalFS!K18/HistoricalFS!J18-1,0) -> 0.077172272 | M6: =IFERROR(HistoricalFS!L18/HistoricalFS!K18-1,0) -> 0.077581813 | O6: =IFERROR(AVERAGE(E6:M6),0) -> 0.097345847 | P6: =IFERROR(MEDIAN(E6:M6),0) -> 0.077581813
B7: EBIT Growth | E7: =IFERROR(HistoricalFS!D27/HistoricalFS!C27-1,0) -> 0.0034317496 | F7: =IFERROR(HistoricalFS!E27/HistoricalFS!D27-1,0) -> 0.070758889 | G7: =IFERROR(HistoricalFS!F27/HistoricalFS!E27-1,0) -> 0.057547222 | H7: =IFERROR(HistoricalFS!G27/HistoricalFS!F27-1,0) -> 0.27197459 | I7: =IFERROR(HistoricalFS!H27/HistoricalFS!G27-1,0) -> 0.13869898 | J7: =IFERROR(HistoricalFS!I27/HistoricalFS!H27-1,0) -> 0.10088082 | K7: =IFERROR(HistoricalFS!J27/HistoricalFS!I27-1,0) -> 0.021423206 | L7: =IFERROR(HistoricalFS!K27/HistoricalFS!J27-1,0) -> 0.087316558 | M7: =IFERROR(HistoricalFS!L27/HistoricalFS!K27-1,0) -> 0.086861915 | O7: =IFERROR(AVERAGE(E7:M7),0) -> 0.093210437 | P7: =IFERROR(MEDIAN(E7:M7),0) -> 0.086861915
B8: Net Profit Growth | E8: =IFERROR(HistoricalFS!D33/HistoricalFS!C33-1,0) -> 0.125188 | F8: =IFERROR(HistoricalFS!E33/HistoricalFS!D33-1,0) -> -0.014939456 | G8: =IFERROR(HistoricalFS!F33/HistoricalFS!E33-1,0) -> 0.10440613 | H8: =IFERROR(HistoricalFS!G33/HistoricalFS!F33-1,0) -> 0.24472391 | I8: =IFERROR(HistoricalFS!H33/HistoricalFS!G33-1,0) -> 0.15265358 | J8: =IFERROR(HistoricalFS!I33/HistoricalFS!H33-1,0) -> 0.078383961 | K8: =IFERROR(HistoricalFS!J33/HistoricalFS!I33-1,0) -> 0.0060727799 | L8: =IFERROR(HistoricalFS!K33/HistoricalFS!J33-1,0) -> 0.074894368 | M8: =IFERROR(HistoricalFS!L33/HistoricalFS!K33-1,0) -> 0.14215983 | O8: =IFERROR(AVERAGE(E8:M8),0) -> 0.10150479 | P8: =IFERROR(MEDIAN(E8:M8),0) -> 0.10440613
B9: Dividend Growth | E9: =IFERROR(HistoricalFS!D41/HistoricalFS!C41-1,0) -> 0.68963897 | F9: =IFERROR(HistoricalFS!E41/HistoricalFS!D41-1,0) -> -0.02583858 | G9: =IFERROR(HistoricalFS!F41/HistoricalFS!E41-1,0) -> -0.17390646 | H9: =IFERROR(HistoricalFS!G41/HistoricalFS!F41-1,0) -> 0.54369512 | I9: =IFERROR(HistoricalFS!H41/HistoricalFS!G41-1,0) -> 0.14865158 | J9: =IFERROR(HistoricalFS!I41/HistoricalFS!H41-1,0) -> 0.096761529 | K9: =IFERROR(HistoricalFS!J41/HistoricalFS!I41-1,0) -> 0.35349861 | L9: =IFERROR(HistoricalFS!K41/HistoricalFS!J41-1,0) -> -0.064855345 | M9: =IFERROR(HistoricalFS!L41/HistoricalFS!K41-1,0) -> 0.116149 | O9: =IFERROR(AVERAGE(E9:M9),0) -> 0.18708827 | P9: =IFERROR(MEDIAN(E9:M9),0) -> 0.116149
B11: Gross Margin | D11: =IFERROR(HistoricalFS!C13,0) -> 0.34862158 | E11: =IFERROR(HistoricalFS!D13,0) -> 0.34212019 | F11: =IFERROR(HistoricalFS!E13,0) -> 0.32934986 | G11: =IFERROR(HistoricalFS!F13,0) -> 0.31479993 | H11: =IFERROR(HistoricalFS!G13,0) -> 0.31831754 | I11: =IFERROR(HistoricalFS!H13,0) -> 0.30271043 | J11: =IFERROR(HistoricalFS!I13,0) -> 0.28539794 | K11: =IFERROR(HistoricalFS!J13,0) -> 0.28398516 | ... M11: =IFERROR(HistoricalFS!L13,0) -> 0.28207669 | O11: =IFERROR(AVERAGE(D11:M11),0) -> 0.309209 | P11: =IFERROR(MEDIAN(D11:M11),0) -> 0.30875518
B12: EBITDA Margin | D12: =IFERROR(HistoricalFS!C19,0) -> 0.27165469 | E12: =IFERROR(HistoricalFS!D19,0) -> 0.26689544 | F12: =IFERROR(HistoricalFS!E19,0) -> 0.24396734 | G12: =IFERROR(HistoricalFS!F19,0) -> 0.24525559 | H12: =IFERROR(HistoricalFS!G19,0) -> 0.27757982 | I12: =IFERROR(HistoricalFS!H19,0) -> 0.25888475 | J12: =IFERROR(HistoricalFS!I19,0) -> 0.23935898 | K12: =IFERROR(HistoricalFS!J19,0) -> 0.2370339 | ... M12: =IFERROR(HistoricalFS!L19,0) -> 0.23666387 | O12: =IFERROR(AVERAGE(D12:M12),0) -> 0.25180208 | P12: =IFERROR(MEDIAN(D12:M12),0) -> 0.24461146
B13: EBIT Margin | D13: =IFERROR((HistoricalFS!C18-HistoricalFS!C24)/HistoricalFS!C6,0) -> 0.24678757 | E13: =IFERROR((HistoricalFS!D18-HistoricalFS!D24)/HistoricalFS!D6,0) -> 0.24047815 | F13: =IFERROR((HistoricalFS!E18-HistoricalFS!E24)/HistoricalFS!E6,0) -> 0.21964318 | G13: =IFERROR((HistoricalFS!F18-HistoricalFS!F24)/HistoricalFS!F6,0) -> 0.2133912 | H13: =IFERROR((HistoricalFS!G18-HistoricalFS!G24)/HistoricalFS!G6,0) -> 0.2450633 | I13: =IFERROR((HistoricalFS!H18-HistoricalFS!H24)/HistoricalFS!H6,0) -> 0.23030886 | J13: =IFERROR((HistoricalFS!I18-HistoricalFS!I24)/HistoricalFS!I6,0) -> 0.21057186 | K13: =IFERROR((HistoricalFS!J18-HistoricalFS!J24)/HistoricalFS!J6,0) -> 0.20659205 | ... M13: =IFERROR((HistoricalFS!L18-HistoricalFS!L24)/HistoricalFS!L6,0) -> 0.20922474 | O13: =IFERROR(AVERAGE(D13:M13),0) -> 0.2233264 | P13: =IFERROR(MEDIAN(D13:M13),0) -> 0.21651719
B14: EBT Margin | D14: =IFERROR(HistoricalFS!C28,0) -> 0.24678757 | E14: =IFERROR(HistoricalFS!D28,0) -> 0.24047815 | F14: =IFERROR(HistoricalFS!E28,0) -> 0.21964318 | G14: =IFERROR(HistoricalFS!F28,0) -> 0.21151876 | H14: =IFERROR(HistoricalFS!G28,0) -> 0.24312246 | I14: =IFERROR(HistoricalFS!H28,0) -> 0.22866468 | J14: =IFERROR(HistoricalFS!I28,0) -> 0.20863682 | K14: =IFERROR(HistoricalFS!J28,0) -> 0.20353355 | ... M14: =IFERROR(HistoricalFS!L28,0) -> 0.20689617 | O14: =IFERROR(AVERAGE(D14:M14),0) -> 0.22179322 | P14: =IFERROR(MEDIAN(D14:M14),0) -> 0.21558097
B15: Net Profit Margin | D15: =IFERROR(HistoricalFS!C34,0) -> 0.16504585 | E15: =IFERROR(HistoricalFS!D34,0) -> 0.18034089 | F15: =IFERROR(HistoricalFS!E34,0) -> 0.15153311 | G15: =IFERROR(HistoricalFS!F34,0) -> 0.15239396 | H15: =IFERROR(HistoricalFS!G34,0) -> 0.17141094 | I15: =IFERROR(HistoricalFS!H34,0) -> 0.16319333 | J15: =IFERROR(HistoricalFS!I34,0) -> 0.14585704 | K15: =IFERROR(HistoricalFS!J34,0) -> 0.14015097 | ... M15: =IFERROR(HistoricalFS!L34,0) -> 0.14800448 | O15: =IFERROR(AVERAGE(D15:M15),0) -> 0.15599638 | P15: =IFERROR(MEDIAN(D15:M15),0) -> 0.15196354
B17: SalesExpenses%Sales | D17: =IFERROR(HistoricalFS!C10,0) -> 0.65137842 | E17: =IFERROR(HistoricalFS!D10,0) -> 0.65787981 | F17: =IFERROR(HistoricalFS!E10,0) -> 0.67065014 | G17: =IFERROR(HistoricalFS!F10,0) -> 0.68520007 | H17: =IFERROR(HistoricalFS!G10,0) -> 0.68168246 | I17: =IFERROR(HistoricalFS!H10,0) -> 0.69728957 | J17: =IFERROR(HistoricalFS!I10,0) -> 0.71460206 | K17: =IFERROR(HistoricalFS!J10,0) -> 0.71601484 | ... M17: =IFERROR(HistoricalFS!L10,0) -> 0.71792331 | O17: =IFERROR(AVERAGE(D17:M17),0) -> 0.690791 | P17: =IFERROR(MEDIAN(D17:M17),0) -> 0.69124482
B18: Depreciation%Sales | D18: =IFERROR(HistoricalFS!C25,0) -> 0.024867122 | E18: =IFERROR(HistoricalFS!D25,0) -> 0.026417288 | F18: =IFERROR(HistoricalFS!E25,0) -> 0.024324161 | G18: =IFERROR(HistoricalFS!F25,0) -> 0.031864392 | H18: =IFERROR(HistoricalFS!G25,0) -> 0.032516522 | I18: =IFERROR(HistoricalFS!H25,0) -> 0.028575891 | J18: =IFERROR(HistoricalFS!I25,0) -> 0.028787125 | K18: =IFERROR(HistoricalFS!J25,0) -> 0.030441856 | ... M18: =IFERROR(HistoricalFS!L25,0) -> 0.027439127 | O18: =IFERROR(AVERAGE(D18:M18),0) -> 0.028475677 | P18: =IFERROR(MEDIAN(D18:M18),0) -> 0.028681508
B19: OperatingIncome%Sales | D19: =IFERROR('Ratio Analysis'!D13,0) -> 0.24678757 | E19: =IFERROR('Ratio Analysis'!E13,0) -> 0.24047815 | F19: =IFERROR('Ratio Analysis'!F13,0) -> 0.21964318 | G19: =IFERROR('Ratio Analysis'!G13,0) -> 0.2133912 | H19: =IFERROR('Ratio Analysis'!H13,0) -> 0.2450633 | I19: =IFERROR('Ratio Analysis'!I13,0) -> 0.23030886 | J19: =IFERROR('Ratio Analysis'!J13,0) -> 0.21057186 | K19: =IFERROR('Ratio Analysis'!K13,0) -> 0.20659205 | ... M19: =IFERROR('Ratio Analysis'!M13,0) -> 0.20922474 | O19: =IFERROR(AVERAGE(D19:M19),0) -> 0.2233264 | P19: =IFERROR(MEDIAN(D19:M19),0) -> 0.21651719
B21: Return on Capital Employed | D21: =IFERROR((HistoricalFS!C18-HistoricalFS!C24)/SUM(HistoricalFS!C47:C49),0) -> 0.24500594 | E21: =IFERROR((HistoricalFS!D18-HistoricalFS!D24)/SUM(HistoricalFS!D47:D49),0) -> 0.26121713 | F21: =IFERROR((HistoricalFS!E18-HistoricalFS!E24)/SUM(HistoricalFS!E47:E49),0) -> 0.27959291 | G21: =IFERROR((HistoricalFS!F18-HistoricalFS!F24)/SUM(HistoricalFS!F47:F49),0) -> 0.27644365 | H21: =IFERROR((HistoricalFS!G18-HistoricalFS!G24)/SUM(HistoricalFS!G47:G49),0) -> 0.30145943 | I21: =IFERROR((HistoricalFS!H18-HistoricalFS!H24)/SUM(HistoricalFS!H47:H49),0) -> 0.34661734 | J21: =IFERROR((HistoricalFS!I18-HistoricalFS!I24)/SUM(HistoricalFS!I47:I49),0) -> 0.3692089 | K21: =IFERROR((HistoricalFS!J18-HistoricalFS!J24)/SUM(HistoricalFS!J47:J49),0) -> 0.32906971 | ... M21: =IFERROR((HistoricalFS!L18-HistoricalFS!L24)/SUM(HistoricalFS!L47:L49),0) -> 0.36635041 | O21: =IFERROR(AVERAGE(D21:M21),0) -> 0.31058223 | P21: =IFERROR(MEDIAN(D21:M21),0) -> 0.31526457
B22: Retained Earnings% | D22: =IFERROR(HistoricalFS!C44,0) -> 0.47875785 | E22: =IFERROR(HistoricalFS!D44,0) -> 0.25573203 | F22: =IFERROR(HistoricalFS!E44,0) -> 0.26384898 | G22: =IFERROR(HistoricalFS!F44,0) -> 0.46321191 | H22: =IFERROR(HistoricalFS!G44,0) -> 0.33401463 | I22: =IFERROR(HistoricalFS!H44,0) -> 0.3447383 | J22: =IFERROR(HistoricalFS!I44,0) -> 0.34277573 | K22: =IFERROR(HistoricalFS!J44,0) -> 0.11532711 | ... M22: =IFERROR(HistoricalFS!L44,0) -> 0.26514126 | O22: =IFERROR(AVERAGE(D22:M22),0) -> 0.30934485 | P22: =IFERROR(MEDIAN(D22:M22),0) -> 0.29957795
B23: Return on Equity% | D23: =IFERROR(HistoricalFS!C33/SUM(HistoricalFS!C47:C48),0) -> 0.16385434 | E23: =IFERROR(HistoricalFS!D33/SUM(HistoricalFS!D47:D48),0) -> 0.1958936 | F23: =IFERROR(HistoricalFS!E33/SUM(HistoricalFS!E47:E48),0) -> 0.19289278 | G23: =IFERROR(HistoricalFS!F33/SUM(HistoricalFS!F47:F48),0) -> 0.21139801 | H23: =IFERROR(HistoricalFS!G33/SUM(HistoricalFS!G47:G48),0) -> 0.22556352 | I23: =IFERROR(HistoricalFS!H33/SUM(HistoricalFS!H47:H48),0) -> 0.26345056 | J23: =IFERROR(HistoricalFS!I33/SUM(HistoricalFS!I47:I48),0) -> 0.28388611 | K23: =IFERROR(HistoricalFS!J33/SUM(HistoricalFS!J47:J48),0) -> 0.24441645 | ... M23: =IFERROR(HistoricalFS!L33/SUM(HistoricalFS!L47:L48),0) -> 0.284765 | O23: =IFERROR(AVERAGE(D23:M23),0) -> 0.23077242 | P23: =IFERROR(MEDIAN(D23:M23),0) -> 0.23358369
B24: Self Sustained Growth Rate | D24: =IFERROR(D22*D23,0) -> 0.078446551 | E24: =IFERROR(E22*E23,0) -> 0.050096268 | F24: =IFERROR(F22*F23,0) -> 0.050894562 | G24: =IFERROR(G22*G23,0) -> 0.097922078 | H24: =IFERROR(H22*H23,0) -> 0.075341515 | I24: =IFERROR(I22*I23,0) -> 0.0908215 | J24: =IFERROR(J22*J23,0) -> 0.097309268 | K24: =IFERROR(K22*K23,0) -> 0.028187843 | ... M24: =IFERROR(M22*M23,0) -> 0.075502951 | O24: =IFERROR(AVERAGE(D24:M24),0) -> 0.070006742 | P24: =IFERROR(MEDIAN(D24:M24),0) -> 0.075422233
B25: Interest Coverage Ratio | D25: =IFERROR((HistoricalFS!C18-HistoricalFS!C24)/HistoricalFS!C21,0) -> 0 | E25: =IFERROR((HistoricalFS!D18-HistoricalFS!D24)/HistoricalFS!D21,0) -> 0 | F25: =IFERROR((HistoricalFS!E18-HistoricalFS!E24)/HistoricalFS!E21,0) -> 0 | G25: =IFERROR((HistoricalFS!F18-HistoricalFS!F24)/HistoricalFS!F21,0) -> 113.96471 | H25: =IFERROR((HistoricalFS!G18-HistoricalFS!G24)/HistoricalFS!G21,0) -> 126.26667 | I25: =IFERROR((HistoricalFS!H18-HistoricalFS!H24)/HistoricalFS!H21,0) -> 140.075 | J25: =IFERROR((HistoricalFS!I18-HistoricalFS!I24)/HistoricalFS!I21,0) -> 108.82042 | K25: =IFERROR((HistoricalFS!J18-HistoricalFS!J24)/HistoricalFS!J21,0) -> 67.546809 | ... M25: =IFERROR((HistoricalFS!L18-HistoricalFS!L24)/HistoricalFS!L21,0) -> 89.850962 | O25: =IFERROR(AVERAGE(D25:M25),0) -> 72.927457 | P25: =IFERROR(MEDIAN(D25:M25),0) -> 86.300481
B27: Debtor Turnover Ratio | D27: =IFERROR(HistoricalFS!C6/HistoricalFS!C59,0) -> 5.557864 | E27: =IFERROR(HistoricalFS!D6/HistoricalFS!D59,0) -> 5.3661543 | F27: =IFERROR(HistoricalFS!E6/HistoricalFS!E59,0) -> 5.5759763 | G27: =IFERROR(HistoricalFS!F6/HistoricalFS!F59,0) -> 4.9110726 | H27: =IFERROR(HistoricalFS!G6/HistoricalFS!G59,0) -> 5.207422 | I27: =IFERROR(HistoricalFS!H6/HistoricalFS!H59,0) -> 5.3591065 | J27: =IFERROR(HistoricalFS!I6/HistoricalFS!I59,0) -> 5.7727738 | K27: =IFERROR(HistoricalFS!J6/HistoricalFS!J59,0) -> 5.0895903 | ... M27: =IFERROR(HistoricalFS!L6/HistoricalFS!L59,0) -> 5.0703866 | O27: =IFERROR(AVERAGE(D27:M27),0) -> 5.3141427 | P27: =IFERROR(MEDIAN(D27:M27),0) -> 5.2950934
B28: Creditor Turnover Ratio | D28: =IFERROR(HistoricalFS!C6/HistoricalFS!C50,0) -> 4.8343922 | E28: =IFERROR(HistoricalFS!D6/HistoricalFS!D50,0) -> 4.8885346 | F28: =IFERROR(HistoricalFS!E6/HistoricalFS!E50,0) -> 4.3244586 | G28: =IFERROR(HistoricalFS!F6/HistoricalFS!F50,0) -> 4.1806419 | H28: =IFERROR(HistoricalFS!G6/HistoricalFS!G50,0) -> 3.8889878 | I28: =IFERROR(HistoricalFS!H6/HistoricalFS!H50,0) -> 3.3878568 | J28: =IFERROR(HistoricalFS!I6/HistoricalFS!I50,0) -> 3.5893128 | K28: =IFERROR(HistoricalFS!J6/HistoricalFS!J50,0) -> 3.8859527 | ... M28: =IFERROR(HistoricalFS!L6/HistoricalFS!L50,0) -> 3.4184845 | O28: =IFERROR(AVERAGE(D28:M28),0) -> 4.0124108 | P28: =IFERROR(MEDIAN(D28:M28),0) -> 3.8874703
B29: Inventory Turnover | D29: =IFERROR(HistoricalFS!C6/HistoricalFS!C60,0) -> 0 | E29: =IFERROR(HistoricalFS!D6/HistoricalFS!D60,0) -> 0 | F29: =IFERROR(HistoricalFS!E6/HistoricalFS!E60,0) -> 0 | G29: =IFERROR(HistoricalFS!F6/HistoricalFS!F60,0) -> 0 | H29: =IFERROR(HistoricalFS!G6/HistoricalFS!G60,0) -> 0 | I29: =IFERROR(HistoricalFS!H6/HistoricalFS!H60,0) -> 0 | J29: =IFERROR(HistoricalFS!I6/HistoricalFS!I60,0) -> 0 | K29: =IFERROR(HistoricalFS!J6/HistoricalFS!J60,0) -> 0 | ... M29: =IFERROR(HistoricalFS!L6/HistoricalFS!L60,0) -> 0 | O29: =IFERROR(AVERAGE(D29:M29),0) -> 0 | P29: =IFERROR(MEDIAN(D29:M29),0) -> 0
B30: Fixed Asset Turnover | D30: =IFERROR(HistoricalFS!C6/HistoricalFS!C53,0) -> 4.8299598 | E30: =IFERROR(HistoricalFS!D6/HistoricalFS!D53,0) -> 5.6085573 | F30: =IFERROR(HistoricalFS!E6/HistoricalFS!E53,0) -> 5.2625716 | G30: =IFERROR(HistoricalFS!F6/HistoricalFS!F53,0) -> 3.8165118 | H30: =IFERROR(HistoricalFS!G6/HistoricalFS!G53,0) -> 3.939306 | I30: =IFERROR(HistoricalFS!H6/HistoricalFS!H53,0) -> 4.7147674 | J30: =IFERROR(HistoricalFS!I6/HistoricalFS!I53,0) -> 5.0219675 | K30: =IFERROR(HistoricalFS!J6/HistoricalFS!J53,0) -> 5.5633191 | ... M30: =IFERROR(HistoricalFS!L6/HistoricalFS!L53,0) -> 5.2901984 | O30: =IFERROR(AVERAGE(D30:M30),0) -> 4.9311524 | P30: =IFERROR(MEDIAN(D30:M30),0) -> 5.1422696
B31: Capital Turnover Ratio | D31: =IFERROR(HistoricalFS!C6/SUM(HistoricalFS!C47:C48),0) -> 0.99278073 | E31: =IFERROR(HistoricalFS!D6/SUM(HistoricalFS!D47:D48),0) -> 1.0862406 | F31: =IFERROR(HistoricalFS!E6/SUM(HistoricalFS!E47:E48),0) -> 1.2729414 | G31: =IFERROR(HistoricalFS!F6/SUM(HistoricalFS!F47:F48),0) -> 1.3871811 | H31: =IFERROR(HistoricalFS!G6/SUM(HistoricalFS!G47:G48),0) -> 1.3159225 | I31: =IFERROR(HistoricalFS!H6/SUM(HistoricalFS!H47:H48),0) -> 1.6143464 | J31: =IFERROR(HistoricalFS!I6/SUM(HistoricalFS!I47:I48),0) -> 1.9463312 | K31: =IFERROR(HistoricalFS!J6/SUM(HistoricalFS!J47:J48),0) -> 1.7439512 | ... M31: =IFERROR(HistoricalFS!L6/SUM(HistoricalFS!L47:L48),0) -> 1.9240296 | O31: =IFERROR(AVERAGE(D31:M31),0) -> 1.4984762 | P31: =IFERROR(MEDIAN(D31:M31),0) -> 1.5007637
B34: Debtor Days | D34: =IFERROR(365/D27,0) -> 65.672712 | E34: =IFERROR(365/E27,0) -> 68.018916 | F34: =IFERROR(365/F27,0) -> 65.459389 | G34: =IFERROR(365/G27,0) -> 74.321849 | H34: =IFERROR(365/H27,0) -> 70.092265 | I34: =IFERROR(365/I27,0) -> 68.108368 | J34: =IFERROR(365/J27,0) -> 63.227837 | K34: =IFERROR(365/K27,0) -> 71.715006 | ... M34: =IFERROR(365/M27,0) -> 71.986622 | O34: =IFERROR(AVERAGE(D34:M34),0) -> 68.837823 | P34: =IFERROR(MEDIAN(D34:M34),0) -> 68.941815
B35: Payable Days | D35: =IFERROR(365/D28,0) -> 75.500701 | E35: =IFERROR(365/E28,0) -> 74.664502 | F35: =IFERROR(365/F28,0) -> 84.403629 | G35: =IFERROR(365/G28,0) -> 87.307167 | H35: =IFERROR(365/H28,0) -> 93.854756 | I35: =IFERROR(365/I28,0) -> 107.73773 | J35: =IFERROR(365/J28,0) -> 101.69078 | K35: =IFERROR(365/K28,0) -> 93.92806 | ... M35: =IFERROR(365/M28,0) -> 106.77246 | O35: =IFERROR(AVERAGE(D35:M35),0) -> 92.383358 | P35: =IFERROR(MEDIAN(D35:M35),0) -> 93.891408
B36: Inventory Days | D36: =IFERROR(365/D29,0) -> 0 | E36: =IFERROR(365/E29,0) -> 0 | F36: =IFERROR(365/F29,0) -> 0 | G36: =IFERROR(365/G29,0) -> 0 | H36: =IFERROR(365/H29,0) -> 0 | I36: =IFERROR(365/I29,0) -> 0 | J36: =IFERROR(365/J29,0) -> 0 | K36: =IFERROR(365/K29,0) -> 0 | ... M36: =IFERROR(365/M29,0) -> 0 | O36: =IFERROR(AVERAGE(D36:M36),0) -> 0 | P36: =IFERROR(MEDIAN(D36:M36),0) -> 0
B37: Cash Conversion Cycle | D37: =D34+D36-D35 -> -9.827989 | E37: =E34+E36-E35 -> -6.6455858 | F37: =F34+F36-F35 -> -18.944239 | G37: =G34+G36-G35 -> -12.985318 | H37: =H34+H36-H35 -> -23.762491 | I37: =I34+I36-I35 -> -39.62936 | J37: =J34+J36-J35 -> -38.462938 | K37: =K34+K36-K35 -> -22.213054 | ... M37: =M34+M36-M35 -> -34.785838 | O37: =IFERROR(AVERAGE(D37:M37),0) -> -23.545535 | P37: =IFERROR(MEDIAN(D37:M37),0) -> -22.987772
B39: CFO/Sales | D39: =IFERROR(HistoricalFS!C76/HistoricalFS!C6,0) -> 0.16837509 | E39: =IFERROR(HistoricalFS!D76/HistoricalFS!D6,0) -> 0.18743087 | F39: =IFERROR(HistoricalFS!E76/HistoricalFS!E6,0) -> 0.17951013 | G39: =IFERROR(HistoricalFS!F76/HistoricalFS!F6,0) -> 0.18727627 | H39: =IFERROR(HistoricalFS!G76/HistoricalFS!G6,0) -> 0.23114898 | I39: =IFERROR(HistoricalFS!H76/HistoricalFS!H6,0) -> 0.19635649 | J39: =IFERROR(HistoricalFS!I76/HistoricalFS!I6,0) -> 0.15307937 | K39: =IFERROR(HistoricalFS!J76/HistoricalFS!J6,0) -> 0.16405284 | ... M39: =IFERROR(HistoricalFS!L76/HistoricalFS!L6,0) -> 0.1902379 | O39: =IFERROR(AVERAGE(D39:M39),0) -> 0.1876463 | P39: =IFERROR(MEDIAN(D39:M39),0) -> 0.18735357
B40: CFO/Total Assets | D40: =IFERROR(HistoricalFS!C76/HistoricalFS!C64,0) -> 0.13868043 | E40: =IFERROR(HistoricalFS!D76/HistoricalFS!D64,0) -> 0.16658055 | F40: =IFERROR(HistoricalFS!E76/HistoricalFS!E64,0) -> 0.17653986 | G40: =IFERROR(HistoricalFS!F76/HistoricalFS!F64,0) -> 0.18521786 | H40: =IFERROR(HistoricalFS!G76/HistoricalFS!G64,0) -> 0.21601511 | I40: =IFERROR(HistoricalFS!H76/HistoricalFS!H64,0) -> 0.20461925 | J40: =IFERROR(HistoricalFS!I76/HistoricalFS!I64,0) -> 0.18031879 | K40: =IFERROR(HistoricalFS!J76/HistoricalFS!J64,0) -> 0.18534039 | ... M40: =IFERROR(HistoricalFS!L76/HistoricalFS!L64,0) -> 0.22027637 | O40: =IFERROR(AVERAGE(D40:M40),0) -> 0.19150988 | P40: =IFERROR(MEDIAN(D40:M40),0) -> 0.18527913
B41: CFO/Total Debt | D41: =IFERROR(HistoricalFS!C76/HistoricalFS!C49,0) -> 0 | E41: =IFERROR(HistoricalFS!D76/HistoricalFS!D49,0) -> 0 | F41: =IFERROR(HistoricalFS!E76/HistoricalFS!E49,0) -> 0 | G41: =IFERROR(HistoricalFS!F76/HistoricalFS!F49,0) -> 3.6699763 | H41: =IFERROR(HistoricalFS!G76/HistoricalFS!G49,0) -> 4.3613146 | I41: =IFERROR(HistoricalFS!H76/HistoricalFS!H49,0) -> 4.363354 | J41: =IFERROR(HistoricalFS!I76/HistoricalFS!I49,0) -> 2.7071936 | K41: =IFERROR(HistoricalFS!J76/HistoricalFS!J49,0) -> 3.015911 | ... M41: =IFERROR(HistoricalFS!L76/HistoricalFS!L49,0) -> 3.7037925 | O41: =IFERROR(AVERAGE(D41:M41),0) -> 2.6160183 | P41: =IFERROR(MEDIAN(D41:M41),0) -> 3.3429436

Sheet 3 Statement Model
B3: Key Assumptions | C3: FY2025A | D3: FY2026A | E3: FY2027F | F3: FY2028F | G3: FY2029F | H3: FY2030F | I3: FY2031F
B4: Revenue Growth % | C4: =HistoricalFS!K7 -> 0.060649444 | D4: =HistoricalFS!L7 -> 0.096079514 | E4: =AVERAGE(C4:D4) -> 0.078364479 | F4: =AVERAGE(D4:E4) -> 0.087221996 | G4: =AVERAGE(E4:F4) -> 0.082793238 | H4: =AVERAGE(F4:G4) -> 0.085007617 | I4: =AVERAGE(G4:H4) -> 0.083900427
B5: COGS % of Sales | C5: =HistoricalFS!K10 -> 0.71528928 | D5: =HistoricalFS!L10 -> 0.71792331 | E5: 0.715 | F5: 0.713 | G5: 0.711 | H5: 0.709 | I5: 0.707
B6: SG&A % of Sales | C6: =HistoricalFS!K16 -> 0.043984294 | D6: =HistoricalFS!L16 -> 0.045412818 | E6: 0.0454 | F6: 0.0454 | G6: 0.0454 | H6: 0.0454 | I6: 0.0454
B7: D&A % of Sales | C7: =HistoricalFS!K25 -> 0.029523284 | D7: =HistoricalFS!L25 -> 0.027439127 | E7: 0.0275 | F7: 0.0275 | G7: 0.0275 | H7: 0.0275 | I7: 0.0275
B8: Effective Tax Rate % | C8: =HistoricalFS!K31 -> 0.31927782 | D8: =HistoricalFS!L31 -> 0.28464369 | E8: 0.275 | F8: 0.275 | G8: 0.275 | H8: 0.275 | I8: 0.275
B9: Interest Rate on Average Borrowings % | C9: =HistoricalFS!K21/AVERAGE(HistoricalFS!J49:K49) -> 0.050162788 | D9: =HistoricalFS!L21/AVERAGE(HistoricalFS!K49:L49) -> 0.047807849 | E9: 0.05 | F9: 0.05 | G9: 0.05 | H9: 0.05 | I9: 0.05
B10: Capex % of Sales | C10: =-(HistoricalFS!K79/HistoricalFS!K6) -> 0.013724768 | D10: =-(HistoricalFS!L79/HistoricalFS!L6) -> 0.015264484 | E10: 0.018 | F10: 0.018 | G10: 0.018 | H10: 0.018 | I10: 0.018
B11: Receivable Days (DSO) | C11: ='Ratio Analysis'!L34 -> 69.775262 | D11: ='Ratio Analysis'!M34 -> 71.986622 | E11: 71 | F11: 70 | G11: 70 | H11: 69 | I11: 69
B12: Other Liabilities % of Sales | C12: =HistoricalFS!K50/HistoricalFS!K6 -> 0.26842138 | D12: =HistoricalFS!L50/HistoricalFS!L6 -> 0.29252729 | E12: 0.29 | F12: 0.29 | G12: 0.29 | H12: 0.29 | I12: 0.29
B13: CWIP % of Sales | C13: =HistoricalFS!K54/HistoricalFS!K6 -> 0.0049941714 | D13: =HistoricalFS!L54/HistoricalFS!L6 -> 0.0029443045 | E13: 0.003 | F13: 0.003 | G13: 0.003 | H13: 0.003 | I13: 0.003
B14: Investments % of Sales | C14: =HistoricalFS!K55/HistoricalFS!K6 -> 0.14443217 | D14: =HistoricalFS!L55/HistoricalFS!L6 -> 0.12247411 | E14: 0.122 | F14: 0.122 | G14: 0.122 | H14: 0.122 | I14: 0.122
B15: Other Non-Current Assets % of Sales | C15: =HistoricalFS!K56/HistoricalFS!K6 -> 0.22618566 | D15: =HistoricalFS!L56/HistoricalFS!L6 -> 0.22769102 | E15: 0.228 | F15: 0.228 | G15: 0.228 | H15: 0.228 | I15: 0.228
B16: Dividend Payout Ratio % | C16: =HistoricalFS!K42 -> 0.77009935 | D16: =HistoricalFS!L42 -> 0.73485874 | E16: 0.73 | F16: 0.73 | G16: 0.73 | H16: 0.73 | I16: 0.73
B17: Shares Outstanding (Cr) | C17: ='Data Sheet'!$B$6 -> 405.80564 | D17: ='Data Sheet'!$B$6 -> 405.80564 | E17: ='Data Sheet'!$B$6 -> 405.80564 | F17: ='Data Sheet'!$B$6 -> 405.80564 | G17: ='Data Sheet'!$B$6 -> 405.80564 | H17: ='Data Sheet'!$B$6 -> 405.80564 | I17: ='Data Sheet'!$B$6 -> 405.80564
B18: New Borrowings / (Repayments) | C18: =HistoricalFS!K49-HistoricalFS!J49 -> -132 | D18: =HistoricalFS!L49-HistoricalFS!K49 -> 949 | E18: 0 | F18: 0 | G18: 0 | H18: 0 | I18: 0
B21: INCOME STATEMENT | C21: =C3 -> FY2025A | D21: =D3 -> FY2026A | E21: =E3 -> FY2027F | F21: =F3 -> FY2028F | G21: =G3 -> FY2029F | H21: =H3 -> FY2030F | I21: =I3 -> FY2031F
B23: Sales | C23: =HistoricalFS!K6 -> 162990 | D23: =HistoricalFS!L6 -> 178650 | E23: =D23*(1+E4) -> 192649.81 | F23: =E23*(1+F4) -> 209453.12 | G23: =F23*(1+G4) -> 226794.42 | H23: =G23*(1+H4) -> 246073.67 | I23: =H23*(1+I4) -> 266719.36
B24: Less: COGS | C24: =HistoricalFS!K9 -> 116585 | D24: =HistoricalFS!L9 -> 128257 | E24: =E23*E5 -> 137744.62 | F24: =F23*F5 -> 149340.07 | G24: =G23*G5 -> 161250.83 | H24: =H23*H5 -> 174466.23 | I24: =I23*I5 -> 188570.58
B25: Gross Profit | C25: =HistoricalFS!K12 -> 46405 | D25: =HistoricalFS!L12 -> 50393 | E25: =E23-E24 -> 54905.197 | F25: =F23-F24 -> 60113.044 | G25: =G23-G24 -> 65543.587 | H25: =H23-H24 -> 71607.438 | I25: =I23-I24 -> 78148.771
B26: Less: SG&A Expenses | C26: =HistoricalFS!K15 -> 7169 | D26: =HistoricalFS!L15 -> 8113 | E26: =E23*E6 -> 8746.3016 | F26: =F23*F6 -> 9509.1714 | G26: =G23*G6 -> 10296.467 | H26: =H23*H6 -> 11171.745 | I26: =I23*I6 -> 12109.059
B27: EBITDA | C27: =C25-C26 -> 39236 | D27: =D25-D26 -> 42280 | E27: =E25-E26 -> 46158.895 | F27: =F25-F26 -> 50603.873 | G27: =G25-G26 -> 55247.12 | H27: =H25-H26 -> 60435.693 | I27: =I25-I26 -> 66039.713
B28: Less: Depreciation & Amortization | C28: =HistoricalFS!K24 -> 4812 | D28: =HistoricalFS!L24 -> 4902 | E28: =E23*E7 -> 5297.8699 | F28: =F23*F7 -> 5759.9607 | G28: =G23*G7 -> 6236.8465 | H28: =H23*H7 -> 6767.0259 | I28: =I23*I7 -> 7334.7823
B29: EBIT | C29: =C27-C28 -> 34424 | D29: =D27-D28 -> 37378 | E29: =E27-E28 -> 40861.026 | F29: =F27-F28 -> 44843.912 | G29: =G27-G28 -> 49010.274 | H29: =H27-H28 -> 53668.667 | I29: =I27-I28 -> 58704.93
B30: Less: Interest Expense | C30: =HistoricalFS!K21 -> 416 | D30: =HistoricalFS!L21 -> 416 | E30: =E110 -> 458.8 | F30: =F110 -> 458.8 | G30: =G110 -> 458.8 | H30: =H110 -> 458.8 | I30: =I110 -> 458.8
B31: Earnings Before Tax (EBT) | C31: =C29-C30 -> 34008 | D31: =D29-D30 -> 36962 | E31: =E29-E30 -> 40402.226 | F31: =F29-F30 -> 44385.112 | G31: =G29-G30 -> 48551.474 | H31: =H29-H30 -> 53209.867 | I31: =I29-I30 -> 58246.13
B32: Less: Tax | C32: =C31*C8 -> 10858 | D32: =D31*D8 -> 10521 | E32: =E31*E8 -> 11110.612 | F32: =F31*F8 -> 12205.906 | G32: =G31*G8 -> 13351.655 | H32: =H31*H8 -> 14632.714 | I32: =I31*I8 -> 16017.686
B33: Net Income | C33: =C31-C32 -> 23150 | D33: =D31-D32 -> 26441 | E33: =E31-E32 -> 29291.614 | F33: =F31-F32 -> 32179.206 | G33: =G31-G32 -> 35199.818 | H33: =H31-H32 -> 38577.154 | I33: =I31-I32 -> 42228.444
B34: Dividends Paid | C34: =HistoricalFS!K92 -> -20289 | D34: =HistoricalFS!L92 -> -18656 | E34: =-E33*E16 -> -21382.878 | F34: =-F33*F16 -> -23490.821 | G34: =-G33*G16 -> -25695.867 | H34: =-H33*H16 -> -28161.322 | I34: =-I33*I16 -> -30826.764
B35: Retained Earnings (to Reserves) | C35: =SUM(C33:C34) -> 2861 | D35: =SUM(D33:D34) -> 7785 | E35: =SUM(E33:E34) -> 7908.7357 | F35: =SUM(F33:F34) -> 8688.3857 | G35: =SUM(G33:G34) -> 9503.9509 | H35: =SUM(H33:H34) -> 10415.832 | I35: =SUM(I33:I34) -> 11401.68
B38: BALANCE SHEET | C38: =C21 -> FY2025A | D38: =D21 -> FY2026A | E38: =E21 -> FY2027F | F38: =F21 -> FY2028F | G38: =G21 -> FY2029F | H38: =H21 -> FY2030F | I38: =I21 -> FY2031F
B40: Assets
B41: Net Block | C41: =HistoricalFS!K53 -> 30961 | D41: =HistoricalFS!L53 -> 33770 | E41: =E94 -> 31939.827 | F41: =F94 -> 29950.022 | G41: =G94 -> 27795.475 | H41: =H94 -> 25457.775 | I41: =I94 -> 22923.941
B42: Capital Work in Progress | C42: =HistoricalFS!K54 -> 814 | D42: =HistoricalFS!L54 -> 526 | E42: =E$23*E13 -> 577.94944 | F42: =F$23*F13 -> 628.35935 | G42: =G$23*G13 -> 680.38325 | H42: =H$23*H13 -> 738.22101 | I42: =I$23*I13 -> 800.15807
B43: Investments | C43: =HistoricalFS!K55 -> 23541 | D43: =HistoricalFS!L55 -> 21880 | E43: =E$23*E14 -> 23503.277 | F43: =F$23*F14 -> 25553.28 | G43: =G$23*G14 -> 27668.919 | H43: =H$23*H14 -> 30020.988 | I43: =I$23*I14 -> 32539.761
B44: Other Non-Current Assets | C44: =HistoricalFS!K56 -> 36866 | D44: =HistoricalFS!L56 -> 40677 | E44: =E$23*E15 -> 43924.158 | F44: =F$23*F15 -> 47755.31 | G44: =G$23*G15 -> 51709.127 | H44: =H$23*H15 -> 56104.797 | I44: =I$23*I15 -> 60812.013
B45: Total Non-Current Assets | C45: =SUM(C40:C44) -> 92182 | D45: =SUM(D40:D44) -> 96853 | E45: =SUM(E40:E44) -> 99945.211 | F45: =SUM(F40:F44) -> 103886.97 | G45: =SUM(G40:G44) -> 107853.9 | H45: =SUM(H40:H44) -> 112321.78 | I45: =SUM(I40:I44) -> 117075.87
B47: Trade Receivables | C47: =HistoricalFS!K59 -> 31158 | D47: =HistoricalFS!L59 -> 35234 | E47: =E23*E11/365 -> 37474.347 | F47: =F23*F11/365 -> 40169.091 | G47: =G23*G11/365 -> 43494.82 | H47: =H23*H11/365 -> 46518.036 | I47: =I23*I11/365 -> 50420.919
B48: Inventory | C48: =HistoricalFS!K60 -> 0 | D48: =HistoricalFS!L60 -> 0 | E48: 0 | F48: 0 | G48: 0 | H48: 0 | I48: 0
B49: Cash & Bank | C49: =HistoricalFS!K61 -> 24455 | D49: =HistoricalFS!L61 -> 22201 | E49: =E86 -> 28385.623 | F49: =F86 -> 35310.462 | G49: =G86 -> 42550.729 | H49: =H86 -> 51066.451 | I49: =I86 -> 59798.404
B50: Total Current Assets | C50: =SUM(C47:C49) -> 55613 | D50: =SUM(D47:D49) -> 57435 | E50: =SUM(E47:E49) -> 65859.971 | F50: =SUM(F47:F49) -> 75479.553 | G50: =SUM(G47:G49) -> 86045.549 | H50: =SUM(H47:H49) -> 97584.487 | I50: =SUM(I47:I49) -> 110219.32
B52: TOTAL ASSETS | C52: =SUM(C45+C50) -> 147795 | D52: =SUM(D45+D50) -> 154288 | E52: =SUM(E45+E50) -> 165805.18 | F52: =SUM(F45+F50) -> 179366.52 | G52: =SUM(G45+G50) -> 193899.45 | H52: =SUM(H45+H50) -> 209906.27 | I52: =SUM(I45+I50) -> 227295.2
B54: Liabilities & Equity
B55: Equity Share Capital | C55: =HistoricalFS!K47 -> 2073 | D55: =HistoricalFS!L47 -> 2024 | E55: =D55 -> 2024 | F55: =E55 -> 2024 | G55: =F55 -> 2024 | H55: =G55 -> 2024 | I55: =H55 -> 2024
B56: Reserves & Surplus | C56: =HistoricalFS!K48 -> 93745 | D56: =HistoricalFS!L48 -> 90828 | E56: =E118 -> 98736.736 | F56: =F118 -> 107425.12 | G56: =G118 -> 116929.07 | H56: =H118 -> 127344.9 | I56: =I118 -> 138746.58
B57: Borrowings | C57: =HistoricalFS!K49 -> 8227 | D57: =HistoricalFS!L49 -> 9176 | E57: =D57 -> 9176 | F57: =E57 -> 9176 | G57: =F57 -> 9176 | H57: =G57 -> 9176 | I57: =H57 -> 9176
B58: Other Liabilities & Provisions | C58: =HistoricalFS!K50 -> 43750 | D58: =HistoricalFS!L50 -> 52260 | E58: =E23*E12 -> 55868.446 | F58: =F23*F12 -> 60741.404 | G58: =G23*G12 -> 65770.381 | H58: =H23*H12 -> 71361.364 | I58: =I23*I12 -> 77348.613
B59: TOTAL LIABILITIES & EQUITY | C59: =SUM(C54:C58) -> 147795 | D59: =SUM(D54:D58) -> 154288 | E59: =SUM(E54:E58) -> 165805.18 | F59: =SUM(F54:F58) -> 179366.52 | G59: =SUM(G54:G58) -> 193899.45 | H59: =SUM(H54:H58) -> 209906.27 | I59: =SUM(I54:I58) -> 227295.2
B61: Balance Check (Assets = Liabilities + Equity) | C61: =IF(C52=C59,"OK") -> OK | D61: =IF(D52=D59,"OK") -> OK | E61: =IF(E52=E59,"OK") -> OK | F61: =IF(F52=F59,"OK") -> OK | G61: =IF(G52=G59,"OK") -> OK | H61: =IF(H52=H59,"OK") -> OK | I61: =IF(I52=I59,"OK") -> OK
B63: CASH FLOW STATEMENT | C63: =C38 -> FY2025A | D63: =D38 -> FY2026A | E63: =E38 -> FY2027F | F63: =F38 -> FY2028F | G63: =G38 -> FY2029F | H63: =H38 -> FY2030F | I63: =I38 -> FY2031F
B65: Operating Activities
B66: Net Income | C66: =C33 -> 23150 | D66: =D33 -> 26441 | E66: =E33 -> 29291.614 | F66: =F33 -> 32179.206 | G66: =G33 -> 35199.818 | H66: =H33 -> 38577.154 | I66: =I33 -> 42228.444
B67: Add: Depreciation & Amortization | C67: =C28 -> 4812 | D67: =D28 -> 4902 | E67: =E28 -> 5297.8699 | F67: =F28 -> 5759.9607 | G67: =G28 -> 6236.8465 | H67: =H28 -> 6767.0259 | I67: =I28 -> 7334.7823
B68: (Increase) / Decrease in Receivables | C68: =HistoricalFS!J59-HistoricalFS!K59 -> -965 | D68: =HistoricalFS!K59-HistoricalFS!L59 -> -4076 | E68: =D47-E47 -> -2240.3474 | F68: =E47-F47 -> -2694.7432 | G68: =F47-G47 -> -3325.7291 | H68: =G47-H47 -> -3023.2165 | I68: =H47-I47 -> -3902.8831
B69: Increase / (Decrease) in Other Liabilities | C69: =HistoricalFS!K50-HistoricalFS!J50 -> 4205 | D69: =HistoricalFS!L50-HistoricalFS!K50 -> 8510 | E69: =E58-D58 -> 3608.4461 | F69: =F58-E58 -> 4872.9574 | G69: =G58-F58 -> 5028.9775 | H69: =H58-G58 -> 5590.9834 | I69: =I58-H58 -> 5987.249
B70: Cash from Operating Activities | C70: =HistoricalFS!K76 -> 35694 | D70: =HistoricalFS!L76 -> 33986 | E70: =SUM(E66:E69) -> 35957.582 | F70: =SUM(F66:F69) -> 40117.381 | G70: =SUM(G66:G69) -> 43139.913 | H70: =SUM(H66:H69) -> 47911.947 | I70: =SUM(I66:I69) -> 51647.593
B72: Investing Activities
B73: Capital Expenditure | C73: =HistoricalFS!K79 -> -2237 | D73: =HistoricalFS!L79 -> -2727 | E73: =-E92 -> -3467.6967 | F73: =-F92 -> -3770.1561 | G73: =-G92 -> -4082.2995 | H73: =-H92 -> -4429.3261 | I73: =-I92 -> -4800.9484
B74: (Increase) in Investments | C74: =HistoricalFS!J55-HistoricalFS!K55 -> 1082 | D74: =HistoricalFS!K55-HistoricalFS!L55 -> 1661 | E74: =D43-E43 -> -1623.2773 | F74: =E43-F43 -> -2050.0028 | G74: =F43-G43 -> -2115.6388 | H74: =G43-H43 -> -2352.0689 | I74: =H43-I43 -> -2518.7737
B75: (Increase) in Capital Work in Progress | C75: =HistoricalFS!J54-HistoricalFS!K54 -> -521 | D75: =HistoricalFS!K54-HistoricalFS!L54 -> 288 | E75: =D42-E42 -> -51.949442 | F75: =E42-F42 -> -50.409904 | G75: =F42-G42 -> -52.023905 | H75: =G42-H42 -> -57.837759 | I75: =H42-I42 -> -61.937058
B76: (Increase) in Other Non-Current Assets | C76: =HistoricalFS!J56-HistoricalFS!K56 -> 1637 | D76: =HistoricalFS!K56-HistoricalFS!L56 -> -3811 | E76: =D44-E44 -> -3247.1576 | F76: =E44-F44 -> -3831.1527 | G76: =F44-G44 -> -3953.8168 | H76: =G44-H44 -> -4395.6697 | I76: =H44-I44 -> -4707.2164
B77: Cash from Investing Activities | C77: =HistoricalFS!K87 -> -1864 | D77: =HistoricalFS!L87 -> 3546 | E77: =SUM(E73:E76) -> -8390.081 | F77: =SUM(F73:F76) -> -9701.7215 | G77: =SUM(G73:G76) -> -10203.779 | H77: =SUM(H73:H76) -> -11234.902 | I77: =SUM(I73:I76) -> -12088.876
B79: Financing Activities
B80: New Borrowings / (Repayments) | C80: =C18 -> -132 | D80: =D18 -> 949 | E80: =E18 -> 0 | F80: =F18 -> 0 | G80: =G18 -> 0 | H80: =H18 -> 0 | I80: =I18 -> 0
B81: Dividends Paid | C81: =C34 -> -20289 | D81: =D34 -> -18656 | E81: =E34 -> -21382.878 | F81: =F34 -> -23490.821 | G81: =G34 -> -25695.867 | H81: =H34 -> -28161.322 | I81: =I34 -> -30826.764
B82: Cash from Financing Activities | C82: =HistoricalFS!K95 -> -24161 | D82: =HistoricalFS!L95 -> -39786 | E82: =SUM(E80:E81) -> -21382.878 | F82: =SUM(F80:F81) -> -23490.821 | G82: =SUM(G80:G81) -> -25695.867 | H82: =SUM(H80:H81) -> -28161.322 | I82: =SUM(I80:I81) -> -30826.764
B84: Net Change in Cash | C84: =C70+C77+C82 -> 9669 | D84: =D70+D77+D82 -> -2254 | E84: =E70+E77+E82 -> 6184.6232 | F84: =F70+F77+F82 -> 6924.839 | G84: =G70+G77+G82 -> 7240.2668 | H84: =H70+H77+H82 -> 8515.7219 | I84: =I70+I77+I82 -> 8731.9525
B85: Beginning Cash & Bank | C85: =HistoricalFS!J61 -> 14786 | D85: =C86 -> 24455 | E85: =D86 -> 22201 | F85: =E86 -> 28385.623 | G85: =F86 -> 35310.462 | H85: =G86 -> 42550.729 | I85: =H86 -> 51066.451
B86: Ending Cash & Bank | C86: =SUM(C84:C85) -> 24455 | D86: =SUM(D84:D85) -> 22201 | E86: =SUM(E84:E85) -> 28385.623 | F86: =SUM(F84:F85) -> 35310.462 | G86: =SUM(G84:G85) -> 42550.729 | H86: =SUM(H84:H85) -> 51066.451 | I86: =SUM(I84:I85) -> 59798.404
B89: SUPPORTING SCHEDULE 1: PP&E & DEPRECIATION
C90: =C63 -> FY2025A | D90: =D63 -> FY2026A | E90: =E63 -> FY2027F | F90: =F63 -> FY2028F | G90: =G63 -> FY2029F | H90: =H63 -> FY2030F | I90: =I63 -> FY2031F
B91: Beginning Net Block | C91: =HistoricalFS!J53 -> 27622 | D91: =HistoricalFS!K53 -> 30961 | E91: =D94 -> 33770 | F91: =E94 -> 31939.827 | G91: =F94 -> 29950.022 | H91: =G94 -> 27795.475 | I91: =H94 -> 25457.775
B92: Add: Capital Expenditure | C92: =-HistoricalFS!K79 -> 2237 | D92: =-HistoricalFS!L79 -> 2727 | E92: =E23*E10 -> 3467.6967 | F92: =F23*F10 -> 3770.1561 | G92: =G23*G10 -> 4082.2995 | H92: =H23*H10 -> 4429.3261 | I92: =I23*I10 -> 4800.9484
B93: Less: Depreciation & Amortization | C93: =C28 -> 4812 | D93: =D28 -> 4902 | E93: =E28 -> 5297.8699 | F93: =F28 -> 5759.9607 | G93: =G28 -> 6236.8465 | H93: =H28 -> 6767.0259 | I93: =I28 -> 7334.7823
B94: Ending Net Block | C94: =HistoricalFS!K53 -> 30961 | D94: =HistoricalFS!L53 -> 33770 | E94: =E91+E92-E93 -> 31939.827 | F94: =F91+F92-F93 -> 29950.022 | G94: =G91+G92-G93 -> 27795.475 | H94: =H91+H92-H93 -> 25457.775 | I94: =I91+I92-I93 -> 22923.941
B96: SUPPORTING SCHEDULE 2: WORKING CAPITAL
C97: =C90 -> FY2025A | D97: =D90 -> FY2026A | E97: =E90 -> FY2027F | F97: =F90 -> FY2028F | G97: =G90 -> FY2029F | H97: =H90 -> FY2030F | I97: =I90 -> FY2031F
B98: Trade Receivables | C98: =HistoricalFS!K59 -> 31158 | D98: =HistoricalFS!L59 -> 35234 | E98: =E47 -> 37474.347 | F98: =F47 -> 40169.091 | G98: =G47 -> 43494.82 | H98: =H47 -> 46518.036 | I98: =I47 -> 50420.919
B99: Other Liabilities & Provisions | C99: =HistoricalFS!K50 -> 43750 | D99: =HistoricalFS!L50 -> 52260 | E99: =E58 -> 55868.446 | F99: =F58 -> 60741.404 | G99: =G58 -> 65770.381 | H99: =H58 -> 71361.364 | I99: =I58 -> 77348.613
B100: Net Working Capital | C100: =C98-C99 -> -12592 | D100: =D98-D99 -> -17026 | E100: =E98-E99 -> -18394.099 | F100: =F98-F99 -> -20572.313 | G100: =G98-G99 -> -22275.561 | H100: =H98-H99 -> -24843.328 | I100: =I98-I99 -> -26927.694
B101: (Increase) / Decrease in Receivables | C101: =C68 -> -965 | D101: =D68 -> -4076 | E101: =E68 -> -2240.3474 | F101: =F68 -> -2694.7432 | G101: =G68 -> -3325.7291 | H101: =H68 -> -3023.2165 | I101: =I68 -> -3902.8831
B102: Increase / (Decrease) in Other Liabilities | C102: =C69 -> 4205 | D102: =D69 -> 8510 | E102: =E69 -> 3608.4461 | F102: =F69 -> 4872.9574 | G102: =G69 -> 5028.9775 | H102: =H69 -> 5590.9834 | I102: =I69 -> 5987.249
B104: SUPPORTING SCHEDULE 3: DEBT
B106: Beginning Borrowings | C106: =HistoricalFS!J49 -> 8359 | D106: =HistoricalFS!K49 -> 8227 | E106: =D57 -> 9176 | F106: =E57 -> 9176 | G106: =F57 -> 9176 | H106: =G57 -> 9176 | I106: =H57 -> 9176
B107: New Borrowings / (Repayments) | C107: =C18 -> -132 | D107: =D18 -> 949 | E107: =E18 -> 0 | F107: =F18 -> 0 | G107: =G18 -> 0 | H107: =H18 -> 0 | I107: =I18 -> 0
B108: Ending Borrowings | C108: =HistoricalFS!K49 -> 8227 | D108: =HistoricalFS!L49 -> 9176 | E108: =SUM(E106:E107) -> 9176 | F108: =SUM(F106:F107) -> 9176 | G108: =SUM(G106:G107) -> 9176 | H108: =SUM(H106:H107) -> 9176 | I108: =SUM(I106:I107) -> 9176
B109: Average Borrowings | C109: =AVERAGE(C108,C106) -> 8293 | D109: =AVERAGE(D108,D106) -> 8701.5 | E109: =AVERAGE(E108,E106) -> 9176 | F109: =AVERAGE(F108,F106) -> 9176 | G109: =AVERAGE(G108,G106) -> 9176 | H109: =AVERAGE(H108,H106) -> 9176 | I109: =AVERAGE(I108,I106) -> 9176
B110: Interest Expense | C110: =C109*C9 -> 416 | D110: =D109*D9 -> 416 | E110: =E109*E9 -> 458.8 | F110: =F109*F9 -> 458.8 | G110: =G109*G9 -> 458.8 | H110: =H109*H9 -> 458.8 | I110: =I109*I9 -> 458.8
B112: SUPPORTING SCHEDULE 4: EQUITY / RESERVES
B113: (₹ Crores, unless stated)
B115: Beginning Reserves | C115: =HistoricalFS!J48 -> 86045 | D115: =HistoricalFS!K48 -> 93745 | E115: =D118 -> 90828 | F115: =E118 -> 98736.736 | G115: =F118 -> 107425.12 | H115: =G118 -> 116929.07 | I115: =H118 -> 127344.9
B116: Add: Net Income | C116: =C66 -> 23150 | D116: =D66 -> 26441 | E116: =E66 -> 29291.614 | F116: =F66 -> 32179.206 | G116: =G66 -> 35199.818 | H116: =H66 -> 38577.154 | I116: =I66 -> 42228.444
B117: Less: Dividends Paid | C117: =-C34 -> 20289 | D117: =-D34 -> 18656 | E117: =-E34 -> 21382.878 | F117: =-F34 -> 23490.821 | G117: =-G34 -> 25695.867 | H117: =-H34 -> 28161.322 | I117: =-I34 -> 30826.764
B118: Ending Reserves | C118: =HistoricalFS!K48 -> 93745 | D118: =HistoricalFS!L48 -> 90828 | E118: =E115+E116-E117 -> 98736.736 | F118: =F115+F116-F117 -> 107425.12 | G118: =G115+G116-G117 -> 116929.07 | H118: =H115+H116-H117 -> 127344.9 | I118: =I115+I116-I117 -> 138746.58

Sheet WACC
B2: Weighted Average Cost of Capital
B4: All figures are in INR unless stated otherwise
B6: Peer Comps
G7: Debt/ | H7: Debt/ | I7: Levered | J7: UnLevered
B8: Name of the Comp | C8: Country | D8: Total Debt | E8: Total Equity | F8: Tax Rate 1 | G8: Equity | H8: Capital | I8: Beta 2 | J8: Beta 3
B9: Infosys | C9: India | D9: 8737 | E9: 464241.67 | F9: 0.3 | G9: 0.1 | H9: =D9/(D9+E9) -> 0.018472292 | I9: 0.758 | J9: =I9/(1+(1-F9)*G9) -> 0.70841121
B10: TCS | C10: India | D10: 11283 | E10: 847356.1 | F10: 0.3 | G10: =D10/E10 -> 0.013315535 | H10: =D10/(D10+E10) -> 0.013140562 | I10: 0.911 | J10: =I10/(1+(1-F10)*G10) -> 0.9025871
B11: HCL Technologies | C11: India | D11: 5215 | E11: 357145.46 | F11: 0.3 | G11: =D11/E11 -> 0.014601894 | H11: =D11/(D11+E11) -> 0.014391747 | I11: 0.838 | J11: =I11/(1+(1-F11)*G11) -> 0.82952119
B12: Wipro | C12: India | D12: 20291 | E12: 179225.03 | F12: 0.3 | G12: =D12/E12 -> 0.11321521 | H12: =D12/(D12+E12) -> 0.1017011 | I12: 0.749 | J12: =I12/(1+(1-F12)*G12) -> 0.69400005
B13: Tech Mahindra | C13: India | D13: 2186.2 | E13: 160830.15 | F13: 0.3 | G13: =D13/E13 -> 0.013593222 | H13: =D13/(D13+E13) -> 0.013410925 | I13: 0.791 | J13: =I13/(1+(1-F13)*G13) -> 0.78354437
B14: LTM | C14: India | D14: 2310 | E14: 138670.47 | F14: 0.3 | G14: =D14/E14 -> 0.016658197 | H14: =D14/(D14+E14) -> 0.016385248 | I14: 1.19 | J14: =I14/(1+(1-F14)*G14) -> 1.1762837
E16: Average | F16: =AVERAGE(F10:F14) -> 0.3 | G16: =AVERAGE(G10:G14) -> 0.034276812 | H16: =AVERAGE(H10:H14) -> 0.031805917 | I16: =AVERAGE(I10:I14) -> 0.8958 | J16: =AVERAGE(J10:J14) -> 0.87718728
E17: Median | F17: =MEDIAN(F10:F14) -> 0.3 | G17: =MEDIAN(G10:G14) -> 0.014601894 | H17: =MEDIAN(H10:H14) -> 0.014391747 | I17: =MEDIAN(I10:I14) -> 0.838 | J17: =MEDIAN(J10:J14) -> 0.82952119
B20: Cost of Debt | G20: Cost of Equity
B22: Pre-tax Cost of Debt | E22: 0.084 | G22: Risk Free Rate | J22: 0.0696
B23: Tax Rate | E23: 0.3 | G23: Equity Risk Premium | J23: 0.065
B24: After Tax Cost of Debt | E24: =E22*(1-E23) -> 0.0588 | G24: Levered Beta 4 | J24: =J33 -> 0.84859648
G25: Cost of Equity | J25: =J22+J23*J24 -> 0.12475877
B28: Capital Structure | G28: Levered Beta
D30: Current | E30: Target | G30: Comps Median Unlevered Beta | J30: =J17 -> 0.82952119
B31: Total Debt | C31: =D9 -> 8737 | D31: =C31/$C$33 -> 0.018472292 | E31: =H16 -> 0.031805917 | G31: Target Debt/Equity | J31: =E35 -> 0.032850765
B32: Market Capitalization | C32: =E9 -> 464241.67 | D32: =C32/$C$33 -> 0.98152771 | E32: =E33-E31 -> 0.96819408 | G32: Tax Rate | J32: =E23 -> 0.3
B33: Total Capitalization | C33: =SUM(C31:C32) -> 472978.67 | D33: =C33/$C$33 -> 1 | E33: =D33 -> 1 | G33: Levered Beta | J33: =J30*(1+(1-J32)*J31) -> 0.84859648
B35: Debt/Equity | D35: =D31/D32 -> 0.018819939 | E35: =E31/E32 -> 0.032850765 | G35: Weighted Average Cost of Capital
I37: Total Cost | J37: Total Weight
G38: Debt Capital | I38: =E24 -> 0.0588 | J38: =E31 -> 0.031805917
G39: Equity Capital | I39: =J25 -> 0.12475877 | J39: =E32 -> 0.96819408
G40: Weighted Average Cost of Capital | J40: =SUMPRODUCT(I38:I39,J38:J39) -> 0.12266089

Sheet Intrinsic Growth
B5: Calculation of ROIC | F5: 44641 | G5: 45007 | H5: 45373 | I5: 45739 | J5: 46105
B7: Current Assets
B8: Trade receivables | F8: ='Raw Data'!J30 -> 22698 | G8: ='Raw Data'!K30 -> 25424 | H8: ='Raw Data'!L30 -> 30193 | I8: ='Raw Data'!M30 -> 31158 | J8: ='Raw Data'!N30 -> 35234
B9: Loans n Advances | F9: ='Raw Data'!J32 -> 2491 | G9: ='Raw Data'!K32 -> 3242 | H9: ='Raw Data'!L32 -> 10330 | I9: ='Raw Data'!M32 -> 6717 | J9: ='Raw Data'!N32 -> 6808
B10: Other asset items | F10: ='Raw Data'!J33 -> 27528 | G10: ='Raw Data'!K33 -> 34766 | H10: ='Raw Data'!L33 -> 28173 | I10: ='Raw Data'!M33 -> 30149 | J10: ='Raw Data'!N33 -> 33869
B11: Total Current Assets | F11: =SUM(F8:F10) -> 52717 | G11: =SUM(G8:G10) -> 63432 | H11: =SUM(H8:H10) -> 68696 | I11: =SUM(I8:I10) -> 68024 | J11: =SUM(J8:J10) -> 75911
B13: Current Liabilites
B14: Trade Payables | F14: ='Raw Data'!J11 -> 4134 | G14: ='Raw Data'!K11 -> 3865 | H14: ='Raw Data'!L11 -> 3956 | I14: ='Raw Data'!M11 -> 4164 | J14: ='Raw Data'!N11 -> 4744
B15: Advance from Customers | F15: ='Raw Data'!J12 -> 0 | G15: ='Raw Data'!K12 -> 0 | H15: ='Raw Data'!L12 -> 0 | I15: ='Raw Data'!M12 -> 0 | J15: ='Raw Data'!N12 -> 0
B16: Other liability items | F16: ='Raw Data'!J13 -> 31385 | G16: ='Raw Data'!K13 -> 36637 | H16: ='Raw Data'!L13 -> 35244 | I16: ='Raw Data'!M13 -> 39201 | J16: ='Raw Data'!N13 -> 47071
B17: Total Current Liabilities | F17: =SUM(F14:F16) -> 35519 | G17: =SUM(G14:G16) -> 40502 | H17: =SUM(H14:H16) -> 39200 | I17: =SUM(I14:I16) -> 43365 | J17: =SUM(J14:J16) -> 51815
A19: # | B19: Net Working Capital | F19: =F11-F17 -> 17198 | G19: =G11-G17 -> 22930 | H19: =H11-H17 -> 29496 | I19: =I11-I17 -> 24659 | J19: =J11-J17 -> 24096
B21: Non-Current Assets
B22: Land | F22: ='Raw Data'!J16 -> 2066 | G22: ='Raw Data'!K16 -> 2054 | H22: ='Raw Data'!L16 -> 2037 | I22: ='Raw Data'!M16 -> 2079 | J22: ='Raw Data'!N16 -> 1990
B23: Building | F23: ='Raw Data'!J17 -> 16760 | G23: ='Raw Data'!K17 -> 16903 | H23: ='Raw Data'!L17 -> 16515 | I23: ='Raw Data'!M17 -> 16376 | J23: ='Raw Data'!N17 -> 17193
B24: Plant Machinery | F24: ='Raw Data'!J18 -> 3210 | G24: ='Raw Data'!K18 -> 3302 | H24: ='Raw Data'!L18 -> 3428 | I24: ='Raw Data'!M18 -> 3461 | J24: ='Raw Data'!N18 -> 3714
B25: Equipments | F25: ='Raw Data'!J19 -> 1427 | G25: ='Raw Data'!K19 -> 1482 | H25: ='Raw Data'!L19 -> 1528 | I25: ='Raw Data'!M19 -> 1628 | J25: ='Raw Data'!N19 -> 1732
B26: Computers | F26: ='Raw Data'!J20 -> 9936 | G26: ='Raw Data'!K20 -> 11898 | H26: ='Raw Data'!L20 -> 12353 | I26: ='Raw Data'!M20 -> 12925 | J26: ='Raw Data'!N20 -> 13600
B27: Furniture n fittings | F27: ='Raw Data'!J21 -> 2278 | G27: ='Raw Data'!K21 -> 2303 | H27: ='Raw Data'!L21 -> 2326 | I27: ='Raw Data'!M21 -> 2340 | J27: ='Raw Data'!N21 -> 2438
B28: Vehicles | F28: ='Raw Data'!J22 -> 71 | G28: ='Raw Data'!K22 -> 60 | H28: ='Raw Data'!L22 -> 62 | I28: ='Raw Data'!M22 -> 72 | J28: ='Raw Data'!N22 -> 70
B29: Intangible Assets | F29: ='Raw Data'!J23 -> 6495 | G29: ='Raw Data'!K23 -> 7594 | H29: ='Raw Data'!L23 -> 7652 | I29: ='Raw Data'!M23 -> 10626 | J29: ='Raw Data'!N23 -> 12729
B30: Other fixed assets | F30: ='Raw Data'!J24 -> 2766 | G30: ='Raw Data'!K24 -> 3281 | H30: ='Raw Data'!L24 -> 3294 | I30: ='Raw Data'!M24 -> 5184 | J30: ='Raw Data'!N24 -> 6296
B31: Gross Block | F31: ='Raw Data'!J25 -> 45009 | G31: ='Raw Data'!K25 -> 48877 | H31: ='Raw Data'!L25 -> 49195 | I31: ='Raw Data'!M25 -> 54691 | J31: ='Raw Data'!N25 -> 59762
B32: Accumulated Depreciation | F32: =-('Raw Data'!J26) -> -19209 | G32: =-('Raw Data'!K26) -> -19652 | H32: =-('Raw Data'!L26) -> -21573 | I32: =-('Raw Data'!M26) -> -23730 | J32: =-('Raw Data'!N26) -> -25992
A33: # | B33: Net Non Current Assets | F33: =SUM(F31:F32) -> 25800 | G33: =SUM(G31:G32) -> 29225 | H33: =SUM(H31:H32) -> 27622 | I33: =SUM(I31:I32) -> 30961 | J33: =SUM(J31:J32) -> 33770
A35: # | B35: Invested Capital | F35: =F33+F19 -> 42998 | G35: =G33+G19 -> 52155 | H35: =H33+H19 -> 57118 | I35: =I33+I19 -> 55620 | J35: =J33+J19 -> 57866
B36: EBIT | F36: =HistoricalFS!H27+HistoricalFS!I21 -> 28099 | G36: =HistoricalFS!I27+HistoricalFS!J21 -> 31091 | H36: =HistoricalFS!J27+HistoricalFS!K21 -> 31693 | I36: =HistoricalFS!K27+HistoricalFS!L21 -> 34424 | J36: =HistoricalFS!L27+HistoricalFS!M21 -> 37392
B37: Marginal Tax Rate | F37: 0.3 | G37: 0.3 | H37: 0.3 | I37: 0.3 | J37: 0.3
B38: NOPAT | F38: =F36*(1-F37) -> 19669.3 | G38: =G36*(1-G37) -> 21763.7 | H38: =H36*(1-H37) -> 22185.1 | I38: =I36*(1-I37) -> 24096.8 | J38: =J36*(1-J37) -> 26174.4
A40: # | B40: ROIC | F40: =F38/F35 -> 0.45744686 | G40: =G38/G35 -> 0.41728885 | H40: =H38/H35 -> 0.38840821 | I40: =I38/I35 -> 0.43323984 | J40: =J38/J35 -> 0.45232779
A43: # | B43: Calculation of Reinvestment Rate | F43: 44641 | G43: 45007 | H43: 45373 | I43: 45739 | J43: 46105
B45: Net Capex | F45: =-'Cash Flow Data'!H11 -> 2161 | G45: =-'Cash Flow Data'!I11 -> 2579 | H45: =-'Cash Flow Data'!J11 -> 2201 | I45: =-'Cash Flow Data'!K11 -> 2237 | J45: =-'Cash Flow Data'!L11 -> 2727
B46: Change In Working Capital | G46: =G19-F19 -> 5732 | H46: =H19-G19 -> 6566 | I46: =I19-H19 -> -4837 | J46: =J19-I19 -> -563
B48: NOPAT | F48: =F38 -> 19669.3 | G48: =G38 -> 21763.7 | H48: =H38 -> 22185.1 | I48: =I38 -> 24096.8 | J48: =J38 -> 26174.4
B50: Reinvestment | G50: =SUM(G45:G46) -> 8311 | H50: =SUM(H45:H46) -> 8767 | I50: =SUM(I45:I46) -> -2600 | J50: =SUM(J45:J46) -> 2164
A52: # | B52: Reinvestment Rate | G52: =G50/G48 -> 0.38187441 | H52: =H50/H48 -> 0.39517514 | I52: =I50/I48 -> -0.10789814 | J52: =J50/J48 -> 0.082676203
I54: 4 Year Average | J54: =AVERAGE(G52:J52) -> 0.1879569
I55: 4 Year Median | J55: =MEDIAN(G52:J52) -> 0.2322753
B58: Calculation of Growth Rate | F58: 44641 | G58: 45007 | H58: 45373 | I58: 45739 | J58: 46105
B60: Reinvestment Rate | G60: =G52 -> 0.38187441 | H60: =H52 -> 0.39517514 | I60: =I52 -> -0.10789814 | J60: =J52 -> 0.082676203
B61: ROIC | G61: =G40 -> 0.41728885 | H61: =H40 -> 0.38840821 | I61: =I40 -> 0.43323984 | J61: =J40 -> 0.45232779
A63: # | B63: Intrinsic Growth | G63: =G61*G60 -> 0.15935193 | H63: =H61*H60 -> 0.15348927 | I63: =I61*I60 -> -0.046745775 | J63: =J61*J60 -> 0.037396744
I65: 4 Year Average | J65: =AVERAGE(G63:J63) -> 0.075873042
I66: 4 Year Median | J66: =MEDIAN(G63:J63) -> 0.095443006

Sheet DCF
B3: Calculation of PV of FCFF | F3: 46102 | G3: 46468 | H3: 46835 | I3: 47202 | J3: 47569 | K3: 47936
B5: EBIT | F5: =HistoricalFS!L27+HistoricalFS!L21 -> 37378 | G5: =F5*(1+$D$20) -> 40945.469 | H5: =G5*(1+$D$20) -> 44853.427 | I5: =H5*(1+$D$20) -> 49134.373 | J5: =I5*(1+$D$20) -> 53823.906 | K5: =J5*(1+$D$20) -> 58961.021
B7: Tax Rate | F7: 0.3 | G7: =F7 -> 0.3 | H7: =G7 -> 0.3 | I7: =H7 -> 0.3 | J7: =I7 -> 0.3 | K7: =J7 -> 0.3
B9: EBIT(1-T) | F9: =F5*(1-F7) -> 26164.6 | G9: =G5*(1-G7) -> 28661.828 | H9: =H5*(1-H7) -> 31397.399 | I9: =I5*(1-I7) -> 34394.061 | J9: =J5*(1-J7) -> 37676.734 | K9: =K5*(1-K7) -> 41272.715
B11: Less: Reinvestment Rate | F11: ='Intrinsic Growth'!J55 -> 0.2322753 | G11: =F11 -> 0.2322753 | H11: =G11 -> 0.2322753 | I11: =H11 -> 0.2322753 | J11: =I11 -> 0.2322753 | K11: =J11 -> 0.2322753
B13: Free Cash Flow to Firm | F13: =F9*(1-F11) -> 20087.21 | G13: =G9*(1-G11) -> 22004.393 | H13: =H9*(1-H11) -> 24104.559 | I13: =I9*(1-I11) -> 26405.17 | J13: =J9*(1-J11) -> 28925.359 | K13: =K9*(1-K11) -> 31686.082
B15: Mid Year Convention | G15: 0.5 | H15: =G15+1 -> 1.5 | I15: =H15+1 -> 2.5 | J15: =I15+1 -> 3.5 | K15: =J15+1 -> 4.5
B16: Discounting Factor | G16: =1/(1+$D$22)^G15 -> 0.94379072 | H16: =1/(1+$D$22)^H15 -> 0.84067302 | I16: =1/(1+$D$22)^I15 -> 0.74882186 | J16: =1/(1+$D$22)^J15 -> 0.66700628 | K16: =1/(1+$D$22)^K15 -> 0.59412979
B18: PV of FCFF | G18: =G13*G16 -> 20767.542 | H18: =H13*H16 -> 20264.052 | I18: =I13*I16 -> 19772.769 | J18: =J13*J16 -> 19293.396 | K18: =K13*K16 -> 18825.645
B20: Excepted Growth | D20: ='Intrinsic Growth'!J66 -> 0.095443006
B21: Terminal Growth | D21: 0.0538
B22: WACC | D22: =WACC!J40 -> 0.12266089
B25: Calculation of Terminal Value
G26: Sensitivity Analysis
B27: FCFF(n+1) | E27: =K13*(1+D21) -> 33390.793 | G27: =E44 -> 985.80001 | H27: 0.115 | I27: 0.12266089 | J27: 0.13931254 | K27: 0.145
B28: WACC | E28: =D22 -> 0.12266089 | G28: 0.03 | H28: 859.74229 | I28: 791.53784 | J28: 676.37366 | K28: 644.71147
B29: Terminal Growth Rate | E29: =D21 -> 0.0538 | G29: 0.04 | H29: 943.4197 | I29: 859.53392 | J29: 721.93813 | K29: 684.96872
G30: 0.0538 | H30: 1103.8014 | I30: 985.80001 | J30: 802.31769 | K30: 755.02163
B31: Terminal Value | E31: =E27/(E28-E29) -> 484902.13 | G31: 0.06 | H31: 1202.059 | I31: 1060.6347 | J31: 847.53663 | K31: 793.9001
G32: 0.07 | H32: 1417.5917 | I32: 1218.4669 | J32: 937.51679 | K32: 870.15208
B34: Calculation of Equity Value per Share
B36: PV of FCFF | E36: =SUM(G18:K18) -> 98923.404
B37: PV of Terminal Value | E37: =E31*K16 -> 288094.8
B38: Value of Operating Asset | E38: =SUM(E36:E37) -> 387018.21
B40: Add: Cash | E40: ='Data Sheet'!K69 -> 22201
B41: Less: Debt | E41: ='Data Sheet'!K59 -> 9176
B42: Value of Equity | E42: =E38+E40-E41 -> 400043.21
B43: No. of Shares | E43: ='Data Sheet'!B6 -> 405.80564
B44: Equity Value per Share | E44: =E42/E43 -> 985.80001
E46: =IF(E44>'Comps-Valuation'!D9,"Undervalued","Overvalued") -> Overvalued

Sheet Comps-Valuation
B3: Amount in Crores
B4: Comparable Company Valuation
D6: Market Data | K6: Financials | O6: Valuation
B7: Company | D7: Share Price | E7: Shares Outstanding | F7: Equity Value | G7: Net Debt | H7: Enterprise Value | K7: Revenue | L7: EBITDA | M7: Net Income | O7: EV/Revenue | P7: EV/EBITDA | Q7: P/E
B9: Infosys | D9: 1134.25 | E9: 405.82 | F9: =D9*E9 -> 460301.34 | G9: -13464 | H9: =F9+G9 -> 446837.34 | K9: 184582 | L9: 48009 | M9: 30325 | O9: =H9/K9 -> 2.4208067 | P9: =H9/L9 -> 9.307366 | Q9: =F9/M9 -> 15.178939
B10: TCS | D10: 2341.2 | E10: 361.81 | F10: =D10*E10 -> 847069.57 | G10: -1625 | H10: =F10+G10 -> 845444.57 | K10: 275859 | L10: 78389 | M10: 50055 | O10: =H10/K10 -> 3.0647707 | P10: =H10/L10 -> 10.785245 | Q10: =F10/M10 -> 16.922776
B11: HCL Technologies | D11: 1331.6 | E11: 271.37 | F11: =D11*E11 -> 361356.29 | G11: -18210 | H11: =F11+G11 -> 343146.29 | K11: 134374 | L11: 29022 | M11: 17434 | O11: =H11/K11 -> 2.5536658 | P11: =H11/L11 -> 11.823661 | Q11: =F11/M11 -> 20.727102
B12: Wipro | D12: 177.95 | E12: 990.47 | F12: =D12*E12 -> 176254.14 | G12: 9735.5 | H12: =F12+G12 -> 185989.64 | K12: 94968 | L12: 22017.7 | M12: 13285.3 | O12: =H12/K12 -> 1.9584453 | P12: =H12/L12 -> 8.4472782 | Q12: =F12/M12 -> 13.266854
B13: Tech Mahindra | D13: 1618.8 | E13: 98.01 | F13: =D13*E13 -> 158658.59 | G13: -2919.2 | H13: =F13+G13 -> 155739.39 | K13: 59176.1 | L13: 9542.3 | M13: 5163 | O13: =H13/K13 -> 2.6317954 | P13: =H13/L13 -> 16.320949 | Q13: =F13/M13 -> 30.729922
B14: LTM | D14: 4581.1 | E14: 29.66 | F14: =D14*E14 -> 135875.43 | G14: -502.4 | H14: =F14+G14 -> 135373.03 | K14: 44075 | L14: 8924.1 | M14: 5196.7 | O14: =H14/K14 -> 3.0714243 | P14: =H14/L14 -> 15.169376 | Q14: =F14/M14 -> 26.146483
B15: Oracle Fin.Serv. | D15: 12107.5 | E15: 8.71 | F15: =D15*E15 -> 105456.33 | G15: -5477.3 | H15: =F15+G15 -> 99979.025 | K15: 8945.1 | L15: 4783.3 | M15: 3412.9 | O15: =H15/K15 -> 11.17696 | P15: =H15/L15 -> 20.901684 | Q15: =F15/M15 -> 30.89933
B16: Persistent Systems | D16: 5705.6 | E16: 15.78 | F16: =D16*E16 -> 90034.368 | G16: -740.8 | H16: =F16+G16 -> 89293.568 | K16: 15718.1 | L16: 3077.15 | M16: 1923.22 | O16: =H16/K16 -> 5.680939 | P16: =H16/L16 -> 29.01827 | Q16: =F16/M16 -> 46.814388
B17: Coforge | D17: 1965.1 | E17: 44.29 | F17: =D17*E17 -> 87034.279 | G17: -371.4 | H17: =F17+G17 -> 86662.879 | K17: 18195.4 | L17: 3498.5 | M17: 1920 | O17: =H17/K17 -> 4.7629005 | P17: =H17/L17 -> 24.771439 | Q17: =F17/M17 -> 45.330354
B18: Mphasis | D18: 2492.4 | E18: 19.09 | F18: =D18*E18 -> 47579.916 | G18: 866.97 | H18: =F18+G18 -> 48446.886 | K18: 16531.21 | L18: 3398.63 | M18: 1910.41 | O18: =H18/K18 -> 2.9306316 | P18: =H18/L18 -> 14.254828 | Q18: =F18/M18 -> 24.905605
B20: High | O20: =MAX(O10:O18) -> 11.17696 | P20: =MAX(P10:P18) -> 29.01827 | Q20: =MAX(Q10:Q18) -> 46.814388
B21: 75th Percentile | O21: =QUARTILE(O10:O18,3) -> 4.7629005 | P21: =QUARTILE(P10:P18,3) -> 20.901684 | Q21: =QUARTILE(Q10:Q18,3) -> 30.89933
B22: Average | O22: =AVERAGE(O10:O18) -> 4.2035036 | P22: =AVERAGE(P10:P18) -> 16.832525 | Q22: =AVERAGE(Q10:Q18) -> 28.415868
B23: Median | O23: =MEDIAN(O10:O18) -> 3.0647707 | P23: =MEDIAN(P10:P18) -> 15.169376 | Q23: =MEDIAN(Q10:Q18) -> 26.146483
B24: 25th Percentile | O24: =QUARTILE(O10:O18,1) -> 2.6317954 | P24: =QUARTILE(P10:P18,1) -> 11.823661 | Q24: =QUARTILE(Q10:Q18,1) -> 20.727102
B25: Low | O25: =MIN(O10:O18) -> 1.9584453 | P25: =MIN(P10:P18) -> 8.4472782 | Q25: =MIN(Q10:Q18) -> 13.266854
B27: Infosys Comparable Valuation | O27: EV/Revenue | P27: EV/EBITDA | Q27: P/E
B29: Implied Enterprise Value | O29: =O23*K9 -> 565701.5 | P29: =P23*L9 -> 728266.56 | Q29: =Q31+Q30 -> 779428.08
B30: Net Debt | O30: =$G$9 -> -13464 | P30: =$G$9 -> -13464 | Q30: =$G$9 -> -13464
B31: Implied Market Value | O31: =O29-O30 -> 579165.5 | P31: =P29-P30 -> 741730.56 | Q31: =Q23*M9 -> 792892.08
B32: Shares Outstanding | O32: =$E$9 -> 405.82 | P32: =$E$9 -> 405.82 | Q32: =$E$9 -> 405.82
B34: Implied Value per Share | O34: =O31/O32 -> 1427.1487 | P34: =P31/P32 -> 1827.7329 | Q34: =Q31/Q32 -> 1953.8024
B36: Source: Screener.in
O37: =IF(O34<$D$9,"Overvalued","Undervalued") -> Undervalued | P37: =IF(P34<$D$9,"Overvalued","Undervalued") -> Undervalued | Q37: =IF(Q34<$D$9,"Overvalued","Undervalued") -> Undervalued

Sheet Dupont Analysis
B3: INFOSYS LTD
B4: (NSE : INFY | BSE Code : 500209)
B5: INR 1,091
B6: 52 Week (High - ₹ 1,728 & Low - ₹ 982)
B8: About The Company
B9: Infosys Limited is an Indian multinational technology company that offers information technology, business consulting, and outsourcing services. Founded in 1981 by seven engineers, the company is headquartered in Bengaluru and considered one of the Big Six Indian IT companies.Infosys was founded by N. R. Narayana Murthy, Nandan Nilekani, Kris Gopalakrishnan, S. D. Shibulal, K. Dinesh, N. S. Raghavan, and Ashok Arora, with an initial capital of $250.
B16: Financial Summary
B67: Return on Equity (ROE)
C68: =HistoricalFS!F3 -> 43921 | D68: =HistoricalFS!G3 -> 44286 | E68: =HistoricalFS!H3 -> 44651 | F68: =HistoricalFS!I3 -> 45016 | G68: =HistoricalFS!J3 -> 45382 | H68: =HistoricalFS!K3 -> 45747 | I68: =HistoricalFS!L3 -> 46112
B69: Net Profit | C69: =HistoricalFS!F33 -> 13836 | D69: =HistoricalFS!G33 -> 17222 | E69: =HistoricalFS!H33 -> 19851 | F69: =HistoricalFS!I33 -> 21407 | G69: =HistoricalFS!J33 -> 21537 | H69: =HistoricalFS!K33 -> 23150 | I69: =HistoricalFS!L33 -> 26441
B70: Average Shareholder Equity | C70: =(('Data Sheet'!E57+'Data Sheet'!E58)+('Data Sheet'!D57+'Data Sheet'!D58)/2) -> 97924 | D70: =(('Data Sheet'!F57+'Data Sheet'!F58)+('Data Sheet'!E57+'Data Sheet'!E58)/2) -> 109076 | E70: =(('Data Sheet'!G57+'Data Sheet'!G58)+('Data Sheet'!F57+'Data Sheet'!F58)/2) -> 113525.5 | F70: =(('Data Sheet'!H57+'Data Sheet'!H58)+('Data Sheet'!G57+'Data Sheet'!G58)/2) -> 113082 | G70: =(('Data Sheet'!I57+'Data Sheet'!I58)+('Data Sheet'!H57+'Data Sheet'!H58)/2) -> 125819.5 | H70: =(('Data Sheet'!J57+'Data Sheet'!J58)+('Data Sheet'!I57+'Data Sheet'!I58)/2) -> 139876 | I70: =(('Data Sheet'!K57+'Data Sheet'!K58)+('Data Sheet'!J57+'Data Sheet'!J58)/2) -> 140761
B71: Return on Equity | C71: =C69/C70 -> 0.14129325 | D71: =D69/D70 -> 0.15788991 | E71: =E69/E70 -> 0.17485939 | F71: =F69/F70 -> 0.18930511 | G71: =G69/G70 -> 0.17117378 | H71: =H69/H70 -> 0.16550373 | I71: =I69/I70 -> 0.18784322
B73: ROE - Dupont Equation
C74: =C68 -> 43921 | D74: =D68 -> 44286 | E74: =E68 -> 44651 | F74: =F68 -> 45016 | G74: =G68 -> 45382 | H74: =H68 -> 45747 | I74: =I68 -> 46112
B75: =B69 -> Net Profit | C75: =C69 -> 13836 | D75: =D69 -> 17222 | E75: =E69 -> 19851 | F75: =F69 -> 21407 | G75: =G69 -> 21537 | H75: =H69 -> 23150 | I75: =I69 -> 26441
B76: Revenue | C76: =HistoricalFS!F6 -> 90791 | D76: =HistoricalFS!G6 -> 100472 | E76: =HistoricalFS!H6 -> 121641 | F76: =HistoricalFS!I6 -> 146767 | G76: =HistoricalFS!J6 -> 153670 | H76: =HistoricalFS!K6 -> 162990 | I76: =HistoricalFS!L6 -> 178650
B77: Net Profit Margin (A) | C77: =C75/C76 -> 0.15239396 | D77: =D75/D76 -> 0.17141094 | E77: =E75/E76 -> 0.16319333 | F77: =F75/F76 -> 0.14585704 | G77: =G75/G76 -> 0.14015097 | H77: =H75/H76 -> 0.14203325 | I77: =I75/I76 -> 0.14800448
B79: Revenue | C79: =C76 -> 90791 | D79: =D76 -> 100472 | E79: =E76 -> 121641 | F79: =F76 -> 146767 | G79: =G76 -> 153670 | H79: =H76 -> 162990 | I79: =I76 -> 178650
B80: Average Total Asset | C80: =(('Data Sheet'!E66+'Data Sheet'!D66)/2) -> 87933 | D80: =(('Data Sheet'!F66+'Data Sheet'!E66)/2) -> 99655.5 | E80: =(('Data Sheet'!G66+'Data Sheet'!F66)/2) -> 112120 | F80: =(('Data Sheet'!H66+'Data Sheet'!G66)/2) -> 120662.5 | G80: =(('Data Sheet'!I66+'Data Sheet'!H66)/2) -> 130308 | H80: =(('Data Sheet'!J66+'Data Sheet'!I66)/2) -> 141907.5 | I80: =(('Data Sheet'!K66+'Data Sheet'!J66)/2) -> 151041.5
B81: Asset Turnover Ratio (B) | C81: =C79/C80 -> 1.032502 | D81: =D79/D80 -> 1.0081932 | E81: =E79/E80 -> 1.0849179 | F81: =F79/F80 -> 1.2163431 | G81: =G79/G80 -> 1.1792829 | H81: =H79/H80 -> 1.1485651 | I81: =I79/I80 -> 1.1827875
B83: =B80 -> Average Total Asset | C83: =C80 -> 87933 | D83: =D80 -> 99655.5 | E83: =E80 -> 112120 | F83: =F80 -> 120662.5 | G83: =G80 -> 130308 | H83: =H80 -> 141907.5 | I83: =I80 -> 151041.5
B84: =B70 -> Average Shareholder Equity | C84: =C70 -> 97924 | D84: =D70 -> 109076 | E84: =E70 -> 113525.5 | F84: =F70 -> 113082 | G84: =G70 -> 125819.5 | H84: =H70 -> 139876 | I84: =I70 -> 140761
B85: Equity Multiplier (C) | C85: =C83/C84 -> 0.8979719 | D85: =D83/D84 -> 0.91363361 | E85: =E83/E84 -> 0.98761952 | F85: =F83/F84 -> 1.0670354 | G85: =G83/G84 -> 1.0356741 | H85: =H83/H84 -> 1.0145236 | I85: =I83/I84 -> 1.0730351
B87: Return on Equity (A*B*C) | C87: =C85*C81*C77 -> 0.14129325 | D87: =D85*D81*D77 -> 0.15788991 | E87: =E85*E81*E77 -> 0.17485939 | F87: =F85*F81*F77 -> 0.18930511 | G87: =G85*G81*G77 -> 0.17117378 | H87: =H85*H81*H77 -> 0.16550373 | I87: =I85*I81*I77 -> 0.18784322
B89: Return on Asset
C90: =C74 -> 43921 | D90: =D74 -> 44286 | E90: =E74 -> 44651 | F90: =F74 -> 45016 | G90: =G74 -> 45382 | H90: =H74 -> 45747 | I90: =I74 -> 46112
B91: Net Profit | C91: =C75 -> 13836 | D91: =D75 -> 17222 | E91: =E75 -> 19851 | F91: =F75 -> 21407 | G91: =G75 -> 21537 | H91: =H75 -> 23150 | I91: =I75 -> 26441
B92: =B83 -> Average Total Asset | C92: =C80 -> 87933 | D92: =D80 -> 99655.5 | E92: =E80 -> 112120 | F92: =F80 -> 120662.5 | G92: =G80 -> 130308 | H92: =H80 -> 141907.5 | I92: =I80 -> 151041.5
B93: Return on Asset | C93: =C91/C92 -> 0.15734707 | D93: =D91/D92 -> 0.17281535 | E93: =E91/E92 -> 0.17705137 | F93: =F91/F92 -> 0.1774122 | G93: =G91/G92 -> 0.16527765 | H93: =H91/H92 -> 0.16313444 | I93: =I91/I92 -> 0.17505785
B95: ROA - Dupont Equation
C96: =C90 -> 43921 | D96: =D90 -> 44286 | E96: =E90 -> 44651 | F96: =F90 -> 45016 | G96: =G90 -> 45382 | H96: =H90 -> 45747 | I96: =I90 -> 46112
B97: =B91 -> Net Profit | C97: =C91 -> 13836 | D97: =D91 -> 17222 | E97: =E91 -> 19851 | F97: =F91 -> 21407 | G97: =G91 -> 21537 | H97: =H91 -> 23150 | I97: =I91 -> 26441
B98: Revenue | C98: =C79 -> 90791 | D98: =D79 -> 100472 | E98: =E79 -> 121641 | F98: =F79 -> 146767 | G98: =G79 -> 153670 | H98: =H79 -> 162990 | I98: =I79 -> 178650
B99: Net Profit Margin (A) | C99: =C97/C98 -> 0.15239396 | D99: =D97/D98 -> 0.17141094 | E99: =E97/E98 -> 0.16319333 | F99: =F97/F98 -> 0.14585704 | G99: =G97/G98 -> 0.14015097 | H99: =H97/H98 -> 0.14203325 | I99: =I97/I98 -> 0.14800448
B101: Revenue | C101: =C98 -> 90791 | D101: =D98 -> 100472 | E101: =E98 -> 121641 | F101: =F98 -> 146767 | G101: =G98 -> 153670 | H101: =H98 -> 162990 | I101: =I98 -> 178650
B102: Average Total Asset | C102: =C92 -> 87933 | D102: =D92 -> 99655.5 | E102: =E92 -> 112120 | F102: =F92 -> 120662.5 | G102: =G92 -> 130308 | H102: =H92 -> 141907.5 | I102: =I92 -> 151041.5
B103: Asset Turnover Ratio (B) | C103: =C101/C102 -> 1.032502 | D103: =D101/D102 -> 1.0081932 | E103: =E101/E102 -> 1.0849179 | F103: =F101/F102 -> 1.2163431 | G103: =G101/G102 -> 1.1792829 | H103: =H101/H102 -> 1.1485651 | I103: =I101/I102 -> 1.1827875
B105: Return on Asset (A*B) | C105: =C103*C99 -> 0.15734707 | D105: =D103*D99 -> 0.17281535 | E105: =E103*E99 -> 0.17705137 | F105: =F103*F99 -> 0.1774122 | G105: =G103*G99 -> 0.16527765 | H105: =H103*H99 -> 0.16313444 | I105: =I103*I99 -> 0.17505785
